Workbook

Sheet Salaire moyen
C2: DETERMINATION DE LA MOYENNE DES SALAIRES PERCUS SUR LES DOUZE (12) DERNIERS MOIS AVANT LA RUPTURE DU CONTRAT
A4: N° | B4: Noms et Prénoms | C4: M-1 | D4: M-2 | E4: M-3 | F4: M-4 | G4: M-5 | H4: M-6 | I4: M-7 | J4: M-8 | K4: M-9 | L4: M-10 | M4: M-11 | N4: M-12 | O4: Total | P4: Moyenne | Q4: Nbre mois
A5: 12 | O5: =SUM(C5:N5) -> 0 | P5: =AVERAGE(C5:N5) -> #DIV/0! | Q5: =+COUNTA(C5:N5) -> 0
A6: 13 | O6: =SUM(C6:N6) -> 0 | P6: =AVERAGE(C6:N6) -> #DIV/0! | Q6: =+COUNTA(C6:N6) -> 0
A7: 14 | O7: =SUM(C7:N7) -> 0 | P7: =AVERAGE(C7:N7) -> #DIV/0! | Q7: =+COUNTA(C7:N7) -> 0
A8: 15 | O8: =SUM(C8:N8) -> 0 | P8: =AVERAGE(C8:N8) -> #DIV/0! | Q8: =+COUNTA(C8:N8) -> 0
A9: 16 | O9: =SUM(C9:N9) -> 0 | P9: =AVERAGE(C9:N9) -> #DIV/0! | Q9: =+COUNTA(C9:N9) -> 0
A10: 17 | O10: =SUM(C10:N10) -> 0 | P10: =AVERAGE(C10:N10) -> #DIV/0! | Q10: =+COUNTA(C10:N10) -> 0
A11: 18 | O11: =SUM(C11:N11) -> 0 | P11: =AVERAGE(C11:N11) -> #DIV/0! | Q11: =+COUNTA(C11:N11) -> 0
A12: 19 | O12: =SUM(C12:N12) -> 0 | P12: =AVERAGE(C12:N12) -> #DIV/0! | Q12: =+COUNTA(C12:N12) -> 0
A13: 20 | P13: =AVERAGE(C13:N13) -> #DIV/0! | Q13: =+COUNTA(C13:N13) -> 0
A14: 21 | P14: =AVERAGE(C14:N14) -> #DIV/0! | Q14: =+COUNTA(C14:N14) -> 0
A15: 22 | P15: =AVERAGE(C15:N15) -> #DIV/0! | Q15: =+COUNTA(C15:N15) -> 0
A16: 23 | P16: =AVERAGE(C16:N16) -> #DIV/0! | Q16: =+COUNTA(C16:N16) -> 0
A17: 24 | P17: =AVERAGE(C17:N17) -> #DIV/0! | Q17: =+COUNTA(C17:N17) -> 0
A18: 25 | P18: =AVERAGE(C18:N18) -> #DIV/0! | Q18: =+COUNTA(C18:N18) -> 0
A19: 26 | P19: =AVERAGE(C19:N19) -> #DIV/0! | Q19: =+COUNTA(C19:N19) -> 0
A20: 27 | P20: =AVERAGE(C20:N20) -> #DIV/0! | Q20: =+COUNTA(C20:N20) -> 0
A21: 28 | P21: =AVERAGE(C21:N21) -> #DIV/0! | Q21: =+COUNTA(C21:N21) -> 0
A22: 29 | P22: =AVERAGE(C22:N22) -> #DIV/0! | Q22: =+COUNTA(C22:N22) -> 0
A23: 30 | P23: =AVERAGE(C23:N23) -> #DIV/0! | Q23: =+COUNTA(C23:N23) -> 0
A24: 31 | P24: =AVERAGE(C24:N24) -> #DIV/0! | Q24: =+COUNTA(C24:N24) -> 0
... A43: 50 | P43: =AVERAGE(C43:N43) -> #DIV/0! | Q43: =+COUNTA(C43:N43) -> 0

Sheet Brute allocat°
A2: Date de début de l'exercice en cours | B2: 45658
A5: Noms et Prénoms | B5: Type de contrat de la ressource | C5: Catégorie (Renseigner si la ressource est en CDI) | D5: Nature de la rupture du contrat | E5: Salaire brut contractuel | F5: Date fin de contrat (renseigner pour les CDD) | G5: Date de rupture du contrat | H5: Période de préavis observé (ressources CDI) | J5: Nombre de jours de crédits de congés au 31/12/N-1 | K5: Nombre de jours de congés consommés au cours de l'exercice N | L5: Nombre de jours de crédits de congés à payer à la ressource. | M5: Durée de contrat restant à courrir (ressources en CDD) | N5: Durée de préavis observée | O5: Salaire Moyen des douze derniers mois | P5: Allocation brute des congés à payer
H6: Début | I6: Fin
A7: =+'Salaire moyen'!B5 -> 0 | B7: CDD | D7: Rupture de l'employé sans accord partie | E7: 169969 | F7: 45894 | G7: 45858 | J7: 16 | K7: 0 | L7: =IFERROR(ROUND((DATEDIF($B$2,G7,"m")+(DATEDIF($B$2,G7,"md"))/30)*2,0)+J7-K7,J7-K7) -> 29 | M7: =+IFERROR(IF(AND(DATEDIF(G7,F7,"y")>=1,DATEDIF(G7,F7,"ym")>=1,DATEDIF(G7,F7,"md")>=1),DATEDIF(G7,F7,"y") & " ans " & DATEDIF(G7,F7,"ym") & " mois " & DATEDIF(G7,F7,"md") & " jours ",IF(AND(DATEDIF(G7,F7,"y")>=1,DATEDIF(G7,F7,"ym")>=1,DATEDIF(G7,F7,"md")<1),DATEDIF(G7,F7,"y") & " ans " & DATEDIF(G7,F7,"ym") & " mois ",IF(AND(DATEDIF(G7,F7,"y")>=1,DATEDIF(G7,F7,"ym")<1,DATEDIF(G7,F7,"md")>=1),DATEDIF(G7,F7,"y") & " ans " & DATEDIF(G7,F7,"md") & " jours ",IF(AND(DATEDIF(G7,F7,"y")>=1,DATEDIF(G7,F7,"ym")<1,DATEDIF(G7,F7,"md")<1),DATEDIF(G7,F7,"y") & " ans ",IF(AND(DATEDIF(G7,F7,"y")<1,DATEDIF(G7,F7,"ym")>=1,DATEDIF(G7,F7,"md")>=1),DATEDIF(G7,F7,"ym") & " mois " & DATEDIF(G7,F7,"md") & " jours ",IF(AND(DATEDIF(G7,F7,"y")<1,DATEDIF(G7,F7,"ym")>=1,DATEDIF(G7,F7,"md")<1),DATEDIF(G7,F7,"ym") & " mois ",IF(AND(DATEDIF(G7,F7,"y")<1,DATEDIF(G7,F7,"ym")<1,DATEDIF(G7,F7,"md")>=1),DATEDIF(G7,F7,"md") & " jours ",)))))))," ") -> 1 mois 5 jours | N7: =+NETWORKDAYS(H7,I7) -> 0 | O7: =+VLOOKUP(A7,'Salaire moyen'!B5:P54,15,FALSE) -> #N/A | P7: =+O7*L7/24 -> #N/A
A8: =+'Salaire moyen'!B6 -> 0 | L8: =IFERROR(ROUND((DATEDIF($B$2,G8,"m")+(DATEDIF($B$2,G8,"md"))/30)*2,0)+J8-K8,J8-K8) -> 0 | M8: =+IFERROR(IF(AND(DATEDIF(G8,F8,"y")>=1,DATEDIF(G8,F8,"ym")>=1,DATEDIF(G8,F8,"md")>=1),DATEDIF(G8,F8,"y") & " ans " & DATEDIF(G8,F8,"ym") & " mois " & DATEDIF(G8,F8,"md") & " jours ",IF(AND(DATEDIF(G8,F8,"y")>=1,DATEDIF(G8,F8,"ym")>=1,DATEDIF(G8,F8,"md")<1),DATEDIF(G8,F8,"y") & " ans " & DATEDIF(G8,F8,"ym") & " mois ",IF(AND(DATEDIF(G8,F8,"y")>=1,DATEDIF(G8,F8,"ym")<1,DATEDIF(G8,F8,"md")>=1),DATEDIF(G8,F8,"y") & " ans " & DATEDIF(G8,F8,"md") & " jours ",IF(AND(DATEDIF(G8,F8,"y")>=1,DATEDIF(G8,F8,"ym")<1,DATEDIF(G8,F8,"md")<1),DATEDIF(G8,F8,"y") & " ans ",IF(AND(DATEDIF(G8,F8,"y")<1,DATEDIF(G8,F8,"ym")>=1,DATEDIF(G8,F8,"md")>=1),DATEDIF(G8,F8,"ym") & " mois " & DATEDIF(G8,F8,"md") & " jours ",IF(AND(DATEDIF(G8,F8,"y")<1,DATEDIF(G8,F8,"ym")>=1,DATEDIF(G8,F8,"md")<1),DATEDIF(G8,F8,"ym") & " mois ",IF(AND(DATEDIF(G8,F8,"y")<1,DATEDIF(G8,F8,"ym")<1,DATEDIF(G8,F8,"md")>=1),DATEDIF(G8,F8,"md") & " jours ",)))))))," ") -> 0 | N8: =+NETWORKDAYS(H8,I8) -> 0 | O8: =+VLOOKUP(A8,'Salaire moyen'!B6:P55,15,FALSE) -> #N/A | P8: =+O8*L8/24 -> #N/A
A9: =+'Salaire moyen'!B7 -> 0 | L9: =IFERROR(ROUND((DATEDIF($B$2,G9,"m")+(DATEDIF($B$2,G9,"md"))/30)*2,0)+J9-K9,J9-K9) -> 0 | M9: =+IFERROR(IF(AND(DATEDIF(G9,F9,"y")>=1,DATEDIF(G9,F9,"ym")>=1,DATEDIF(G9,F9,"md")>=1),DATEDIF(G9,F9,"y") & " ans " & DATEDIF(G9,F9,"ym") & " mois " & DATEDIF(G9,F9,"md") & " jours ",IF(AND(DATEDIF(G9,F9,"y")>=1,DATEDIF(G9,F9,"ym")>=1,DATEDIF(G9,F9,"md")<1),DATEDIF(G9,F9,"y") & " ans " & DATEDIF(G9,F9,"ym") & " mois ",IF(AND(DATEDIF(G9,F9,"y")>=1,DATEDIF(G9,F9,"ym")<1,DATEDIF(G9,F9,"md")>=1),DATEDIF(G9,F9,"y") & " ans " & DATEDIF(G9,F9,"md") & " jours ",IF(AND(DATEDIF(G9,F9,"y")>=1,DATEDIF(G9,F9,"ym")<1,DATEDIF(G9,F9,"md")<1),DATEDIF(G9,F9,"y") & " ans ",IF(AND(DATEDIF(G9,F9,"y")<1,DATEDIF(G9,F9,"ym")>=1,DATEDIF(G9,F9,"md")>=1),DATEDIF(G9,F9,"ym") & " mois " & DATEDIF(G9,F9,"md") & " jours ",IF(AND(DATEDIF(G9,F9,"y")<1,DATEDIF(G9,F9,"ym")>=1,DATEDIF(G9,F9,"md")<1),DATEDIF(G9,F9,"ym") & " mois ",IF(AND(DATEDIF(G9,F9,"y")<1,DATEDIF(G9,F9,"ym")<1,DATEDIF(G9,F9,"md")>=1),DATEDIF(G9,F9,"md") & " jours ",)))))))," ") -> 0 | N9: =+NETWORKDAYS(H9,I9) -> 0 | O9: =+VLOOKUP(A9,'Salaire moyen'!B7:P56,15,FALSE) -> #N/A | P9: =+O9*L9/24 -> #N/A
A10: =+'Salaire moyen'!B8 -> 0 | L10: =IFERROR(ROUND((DATEDIF($B$2,G10,"m")+(DATEDIF($B$2,G10,"md"))/30)*2,0)+J10-K10,J10-K10) -> 0 | M10: =+IFERROR(IF(AND(DATEDIF(G10,F10,"y")>=1,DATEDIF(G10,F10,"ym")>=1,DATEDIF(G10,F10,"md")>=1),DATEDIF(G10,F10,"y") & " ans " & DATEDIF(G10,F10,"ym") & " mois " & DATEDIF(G10,F10,"md") & " jours ",IF(AND(DATEDIF(G10,F10,"y")>=1,DATEDIF(G10,F10,"ym")>=1,DATEDIF(G10,F10,"md")<1),DATEDIF(G10,F10,"y") & " ans " & DATEDIF(G10,F10,"ym") & " mois ",IF(AND(DATEDIF(G10,F10,"y")>=1,DATEDIF(G10,F10,"ym")<1,DATEDIF(G10,F10,"md")>=1),DATEDIF(G10,F10,"y") & " ans " & DATEDIF(G10,F10,"md") & " jours ",IF(AND(DATEDIF(G10,F10,"y")>=1,DATEDIF(G10,F10,"ym")<1,DATEDIF(G10,F10,"md")<1),DATEDIF(G10,F10,"y") & " ans ",IF(AND(DATEDIF(G10,F10,"y")<1,DATEDIF(G10,F10,"ym")>=1,DATEDIF(G10,F10,"md")>=1),DATEDIF(G10,F10,"ym") & " mois " & DATEDIF(G10,F10,"md") & " jours ",IF(AND(DATEDIF(G10,F10,"y")<1,DATEDIF(G10,F10,"ym")>=1,DATEDIF(G10,F10,"md")<1),DATEDIF(G10,F10,"ym") & " mois ",IF(AND(DATEDIF(G10,F10,"y")<1,DATEDIF(G10,F10,"ym")<1,DATEDIF(G10,F10,"md")>=1),DATEDIF(G10,F10,"md") & " jours ",)))))))," ") -> 0 | N10: =+NETWORKDAYS(H10,I10) -> 0 | O10: =+VLOOKUP(A10,'Salaire moyen'!B8:P57,15,FALSE) -> #N/A | P10: =+O10*L10/24 -> #N/A
A11: =+'Salaire moyen'!B9 -> 0 | L11: =IFERROR(ROUND((DATEDIF($B$2,G11,"m")+(DATEDIF($B$2,G11,"md"))/30)*2,0)+J11-K11,J11-K11) -> 0 | M11: =+IFERROR(IF(AND(DATEDIF(G11,F11,"y")>=1,DATEDIF(G11,F11,"ym")>=1,DATEDIF(G11,F11,"md")>=1),DATEDIF(G11,F11,"y") & " ans " & DATEDIF(G11,F11,"ym") & " mois " & DATEDIF(G11,F11,"md") & " jours ",IF(AND(DATEDIF(G11,F11,"y")>=1,DATEDIF(G11,F11,"ym")>=1,DATEDIF(G11,F11,"md")<1),DATEDIF(G11,F11,"y") & " ans " & DATEDIF(G11,F11,"ym") & " mois ",IF(AND(DATEDIF(G11,F11,"y")>=1,DATEDIF(G11,F11,"ym")<1,DATEDIF(G11,F11,"md")>=1),DATEDIF(G11,F11,"y") & " ans " & DATEDIF(G11,F11,"md") & " jours ",IF(AND(DATEDIF(G11,F11,"y")>=1,DATEDIF(G11,F11,"ym")<1,DATEDIF(G11,F11,"md")<1),DATEDIF(G11,F11,"y") & " ans ",IF(AND(DATEDIF(G11,F11,"y")<1,DATEDIF(G11,F11,"ym")>=1,DATEDIF(G11,F11,"md")>=1),DATEDIF(G11,F11,"ym") & " mois " & DATEDIF(G11,F11,"md") & " jours ",IF(AND(DATEDIF(G11,F11,"y")<1,DATEDIF(G11,F11,"ym")>=1,DATEDIF(G11,F11,"md")<1),DATEDIF(G11,F11,"ym") & " mois ",IF(AND(DATEDIF(G11,F11,"y")<1,DATEDIF(G11,F11,"ym")<1,DATEDIF(G11,F11,"md")>=1),DATEDIF(G11,F11,"md") & " jours ",)))))))," ") | N11: =+NETWORKDAYS(H11,I11) -> 0 | O11: =+VLOOKUP(A11,'Salaire moyen'!B9:P58,15,FALSE) -> #N/A | P11: =+O11*L11/24 -> #N/A
A12: =+'Salaire moyen'!B10 -> 0 | L12: =IFERROR(ROUND((DATEDIF($B$2,G12,"m")+(DATEDIF($B$2,G12,"md"))/30)*2,0)+J12-K12,J12-K12) -> 0 | M12: =+IFERROR(IF(AND(DATEDIF(G12,F12,"y")>=1,DATEDIF(G12,F12,"ym")>=1,DATEDIF(G12,F12,"md")>=1),DATEDIF(G12,F12,"y") & " ans " & DATEDIF(G12,F12,"ym") & " mois " & DATEDIF(G12,F12,"md") & " jours ",IF(AND(DATEDIF(G12,F12,"y")>=1,DATEDIF(G12,F12,"ym")>=1,DATEDIF(G12,F12,"md")<1),DATEDIF(G12,F12,"y") & " ans " & DATEDIF(G12,F12,"ym") & " mois ",IF(AND(DATEDIF(G12,F12,"y")>=1,DATEDIF(G12,F12,"ym")<1,DATEDIF(G12,F12,"md")>=1),DATEDIF(G12,F12,"y") & " ans " & DATEDIF(G12,F12,"md") & " jours ",IF(AND(DATEDIF(G12,F12,"y")>=1,DATEDIF(G12,F12,"ym")<1,DATEDIF(G12,F12,"md")<1),DATEDIF(G12,F12,"y") & " ans ",IF(AND(DATEDIF(G12,F12,"y")<1,DATEDIF(G12,F12,"ym")>=1,DATEDIF(G12,F12,"md")>=1),DATEDIF(G12,F12,"ym") & " mois " & DATEDIF(G12,F12,"md") & " jours ",IF(AND(DATEDIF(G12,F12,"y")<1,DATEDIF(G12,F12,"ym")>=1,DATEDIF(G12,F12,"md")<1),DATEDIF(G12,F12,"ym") & " mois ",IF(AND(DATEDIF(G12,F12,"y")<1,DATEDIF(G12,F12,"ym")<1,DATEDIF(G12,F12,"md")>=1),DATEDIF(G12,F12,"md") & " jours ",)))))))," ") -> 0 | N12: =+NETWORKDAYS(H12,I12) -> 0 | O12: =+VLOOKUP(A12,'Salaire moyen'!B10:P59,15,FALSE) -> #N/A | P12: =+O12*L12/24 -> #N/A
A13: =+'Salaire moyen'!B11 -> 0 | L13: =IFERROR(ROUND((DATEDIF($B$2,G13,"m")+(DATEDIF($B$2,G13,"md"))/30)*2,0)+J13-K13,J13-K13) -> 0 | M13: =+IFERROR(IF(AND(DATEDIF(G13,F13,"y")>=1,DATEDIF(G13,F13,"ym")>=1,DATEDIF(G13,F13,"md")>=1),DATEDIF(G13,F13,"y") & " ans " & DATEDIF(G13,F13,"ym") & " mois " & DATEDIF(G13,F13,"md") & " jours ",IF(AND(DATEDIF(G13,F13,"y")>=1,DATEDIF(G13,F13,"ym")>=1,DATEDIF(G13,F13,"md")<1),DATEDIF(G13,F13,"y") & " ans " & DATEDIF(G13,F13,"ym") & " mois ",IF(AND(DATEDIF(G13,F13,"y")>=1,DATEDIF(G13,F13,"ym")<1,DATEDIF(G13,F13,"md")>=1),DATEDIF(G13,F13,"y") & " ans " & DATEDIF(G13,F13,"md") & " jours ",IF(AND(DATEDIF(G13,F13,"y")>=1,DATEDIF(G13,F13,"ym")<1,DATEDIF(G13,F13,"md")<1),DATEDIF(G13,F13,"y") & " ans ",IF(AND(DATEDIF(G13,F13,"y")<1,DATEDIF(G13,F13,"ym")>=1,DATEDIF(G13,F13,"md")>=1),DATEDIF(G13,F13,"ym") & " mois " & DATEDIF(G13,F13,"md") & " jours ",IF(AND(DATEDIF(G13,F13,"y")<1,DATEDIF(G13,F13,"ym")>=1,DATEDIF(G13,F13,"md")<1),DATEDIF(G13,F13,"ym") & " mois ",IF(AND(DATEDIF(G13,F13,"y")<1,DATEDIF(G13,F13,"ym")<1,DATEDIF(G13,F13,"md")>=1),DATEDIF(G13,F13,"md") & " jours ",)))))))," ") -> 0 | N13: =+NETWORKDAYS(H13,I13) -> 0 | O13: =+VLOOKUP(A13,'Salaire moyen'!B11:P60,15,FALSE) -> #N/A | P13: =+O13*L13/24 -> #N/A
A14: =+'Salaire moyen'!B12 -> 0 | L14: =IFERROR(ROUND((DATEDIF($B$2,G14,"m")+(DATEDIF($B$2,G14,"md"))/30)*2,0)+J14-K14,J14-K14) -> 0 | M14: =+IFERROR(IF(AND(DATEDIF(G14,F14,"y")>=1,DATEDIF(G14,F14,"ym")>=1,DATEDIF(G14,F14,"md")>=1),DATEDIF(G14,F14,"y") & " ans " & DATEDIF(G14,F14,"ym") & " mois " & DATEDIF(G14,F14,"md") & " jours ",IF(AND(DATEDIF(G14,F14,"y")>=1,DATEDIF(G14,F14,"ym")>=1,DATEDIF(G14,F14,"md")<1),DATEDIF(G14,F14,"y") & " ans " & DATEDIF(G14,F14,"ym") & " mois ",IF(AND(DATEDIF(G14,F14,"y")>=1,DATEDIF(G14,F14,"ym")<1,DATEDIF(G14,F14,"md")>=1),DATEDIF(G14,F14,"y") & " ans " & DATEDIF(G14,F14,"md") & " jours ",IF(AND(DATEDIF(G14,F14,"y")>=1,DATEDIF(G14,F14,"ym")<1,DATEDIF(G14,F14,"md")<1),DATEDIF(G14,F14,"y") & " ans ",IF(AND(DATEDIF(G14,F14,"y")<1,DATEDIF(G14,F14,"ym")>=1,DATEDIF(G14,F14,"md")>=1),DATEDIF(G14,F14,"ym") & " mois " & DATEDIF(G14,F14,"md") & " jours ",IF(AND(DATEDIF(G14,F14,"y")<1,DATEDIF(G14,F14,"ym")>=1,DATEDIF(G14,F14,"md")<1),DATEDIF(G14,F14,"ym") & " mois ",IF(AND(DATEDIF(G14,F14,"y")<1,DATEDIF(G14,F14,"ym")<1,DATEDIF(G14,F14,"md")>=1),DATEDIF(G14,F14,"md") & " jours ",)))))))," ") -> 0 | N14: =+NETWORKDAYS(H14,I14) -> 0 | O14: =+VLOOKUP(A14,'Salaire moyen'!B12:P61,15,FALSE) -> #N/A | P14: =+O14*L14/24 -> #N/A
A15: =+'Salaire moyen'!B13 -> 0 | L15: =IFERROR(ROUND((DATEDIF($B$2,G15,"m")+(DATEDIF($B$2,G15,"md"))/30)*2,0)+J15-K15,J15-K15) -> 0 | M15: =+IFERROR(IF(AND(DATEDIF(G15,F15,"y")>=1,DATEDIF(G15,F15,"ym")>=1,DATEDIF(G15,F15,"md")>=1),DATEDIF(G15,F15,"y") & " ans " & DATEDIF(G15,F15,"ym") & " mois " & DATEDIF(G15,F15,"md") & " jours ",IF(AND(DATEDIF(G15,F15,"y")>=1,DATEDIF(G15,F15,"ym")>=1,DATEDIF(G15,F15,"md")<1),DATEDIF(G15,F15,"y") & " ans " & DATEDIF(G15,F15,"ym") & " mois ",IF(AND(DATEDIF(G15,F15,"y")>=1,DATEDIF(G15,F15,"ym")<1,DATEDIF(G15,F15,"md")>=1),DATEDIF(G15,F15,"y") & " ans " & DATEDIF(G15,F15,"md") & " jours ",IF(AND(DATEDIF(G15,F15,"y")>=1,DATEDIF(G15,F15,"ym")<1,DATEDIF(G15,F15,"md")<1),DATEDIF(G15,F15,"y") & " ans ",IF(AND(DATEDIF(G15,F15,"y")<1,DATEDIF(G15,F15,"ym")>=1,DATEDIF(G15,F15,"md")>=1),DATEDIF(G15,F15,"ym") & " mois " & DATEDIF(G15,F15,"md") & " jours ",IF(AND(DATEDIF(G15,F15,"y")<1,DATEDIF(G15,F15,"ym")>=1,DATEDIF(G15,F15,"md")<1),DATEDIF(G15,F15,"ym") & " mois ",IF(AND(DATEDIF(G15,F15,"y")<1,DATEDIF(G15,F15,"ym")<1,DATEDIF(G15,F15,"md")>=1),DATEDIF(G15,F15,"md") & " jours ",)))))))," ") -> 0 | N15: =+NETWORKDAYS(H15,I15) -> 0 | O15: =+VLOOKUP(A15,'Salaire moyen'!B13:P62,15,FALSE) -> #N/A | P15: =+O15*L15/24 -> #N/A
A16: =+'Salaire moyen'!B14 -> 0 | L16: =IFERROR(ROUND((DATEDIF($B$2,G16,"m")+(DATEDIF($B$2,G16,"md"))/30)*2,0)+J16-K16,J16-K16) -> 0 | M16: =+IFERROR(IF(AND(DATEDIF(G16,F16,"y")>=1,DATEDIF(G16,F16,"ym")>=1,DATEDIF(G16,F16,"md")>=1),DATEDIF(G16,F16,"y") & " ans " & DATEDIF(G16,F16,"ym") & " mois " & DATEDIF(G16,F16,"md") & " jours ",IF(AND(DATEDIF(G16,F16,"y")>=1,DATEDIF(G16,F16,"ym")>=1,DATEDIF(G16,F16,"md")<1),DATEDIF(G16,F16,"y") & " ans " & DATEDIF(G16,F16,"ym") & " mois ",IF(AND(DATEDIF(G16,F16,"y")>=1,DATEDIF(G16,F16,"ym")<1,DATEDIF(G16,F16,"md")>=1),DATEDIF(G16,F16,"y") & " ans " & DATEDIF(G16,F16,"md") & " jours ",IF(AND(DATEDIF(G16,F16,"y")>=1,DATEDIF(G16,F16,"ym")<1,DATEDIF(G16,F16,"md")<1),DATEDIF(G16,F16,"y") & " ans ",IF(AND(DATEDIF(G16,F16,"y")<1,DATEDIF(G16,F16,"ym")>=1,DATEDIF(G16,F16,"md")>=1),DATEDIF(G16,F16,"ym") & " mois " & DATEDIF(G16,F16,"md") & " jours ",IF(AND(DATEDIF(G16,F16,"y")<1,DATEDIF(G16,F16,"ym")>=1,DATEDIF(G16,F16,"md")<1),DATEDIF(G16,F16,"ym") & " mois ",IF(AND(DATEDIF(G16,F16,"y")<1,DATEDIF(G16,F16,"ym")<1,DATEDIF(G16,F16,"md")>=1),DATEDIF(G16,F16,"md") & " jours ",)))))))," ") -> 0 | N16: =+NETWORKDAYS(H16,I16) -> 0 | O16: =+VLOOKUP(A16,'Salaire moyen'!B14:P63,15,FALSE) -> #N/A | P16: =+O16*L16/24 -> #N/A
A17: =+'Salaire moyen'!B15 -> 0 | L17: =IFERROR(ROUND((DATEDIF($B$2,G17,"m")+(DATEDIF($B$2,G17,"md"))/30)*2,0)+J17-K17,J17-K17) -> 0 | M17: =+IFERROR(IF(AND(DATEDIF(G17,F17,"y")>=1,DATEDIF(G17,F17,"ym")>=1,DATEDIF(G17,F17,"md")>=1),DATEDIF(G17,F17,"y") & " ans " & DATEDIF(G17,F17,"ym") & " mois " & DATEDIF(G17,F17,"md") & " jours ",IF(AND(DATEDIF(G17,F17,"y")>=1,DATEDIF(G17,F17,"ym")>=1,DATEDIF(G17,F17,"md")<1),DATEDIF(G17,F17,"y") & " ans " & DATEDIF(G17,F17,"ym") & " mois ",IF(AND(DATEDIF(G17,F17,"y")>=1,DATEDIF(G17,F17,"ym")<1,DATEDIF(G17,F17,"md")>=1),DATEDIF(G17,F17,"y") & " ans " & DATEDIF(G17,F17,"md") & " jours ",IF(AND(DATEDIF(G17,F17,"y")>=1,DATEDIF(G17,F17,"ym")<1,DATEDIF(G17,F17,"md")<1),DATEDIF(G17,F17,"y") & " ans ",IF(AND(DATEDIF(G17,F17,"y")<1,DATEDIF(G17,F17,"ym")>=1,DATEDIF(G17,F17,"md")>=1),DATEDIF(G17,F17,"ym") & " mois " & DATEDIF(G17,F17,"md") & " jours ",IF(AND(DATEDIF(G17,F17,"y")<1,DATEDIF(G17,F17,"ym")>=1,DATEDIF(G17,F17,"md")<1),DATEDIF(G17,F17,"ym") & " mois ",IF(AND(DATEDIF(G17,F17,"y")<1,DATEDIF(G17,F17,"ym")<1,DATEDIF(G17,F17,"md")>=1),DATEDIF(G17,F17,"md") & " jours ",)))))))," ") -> 0 | N17: =+NETWORKDAYS(H17,I17) -> 0 | O17: =+VLOOKUP(A17,'Salaire moyen'!B15:P64,15,FALSE) -> #N/A | P17: =+O17*L17/24 -> #N/A
A18: =+'Salaire moyen'!B16 -> 0 | L18: =IFERROR(ROUND((DATEDIF($B$2,G18,"m")+(DATEDIF($B$2,G18,"md"))/30)*2,0)+J18-K18,J18-K18) -> 0 | M18: =+IFERROR(IF(AND(DATEDIF(G18,F18,"y")>=1,DATEDIF(G18,F18,"ym")>=1,DATEDIF(G18,F18,"md")>=1),DATEDIF(G18,F18,"y") & " ans " & DATEDIF(G18,F18,"ym") & " mois " & DATEDIF(G18,F18,"md") & " jours ",IF(AND(DATEDIF(G18,F18,"y")>=1,DATEDIF(G18,F18,"ym")>=1,DATEDIF(G18,F18,"md")<1),DATEDIF(G18,F18,"y") & " ans " & DATEDIF(G18,F18,"ym") & " mois ",IF(AND(DATEDIF(G18,F18,"y")>=1,DATEDIF(G18,F18,"ym")<1,DATEDIF(G18,F18,"md")>=1),DATEDIF(G18,F18,"y") & " ans " & DATEDIF(G18,F18,"md") & " jours ",IF(AND(DATEDIF(G18,F18,"y")>=1,DATEDIF(G18,F18,"ym")<1,DATEDIF(G18,F18,"md")<1),DATEDIF(G18,F18,"y") & " ans ",IF(AND(DATEDIF(G18,F18,"y")<1,DATEDIF(G18,F18,"ym")>=1,DATEDIF(G18,F18,"md")>=1),DATEDIF(G18,F18,"ym") & " mois " & DATEDIF(G18,F18,"md") & " jours ",IF(AND(DATEDIF(G18,F18,"y")<1,DATEDIF(G18,F18,"ym")>=1,DATEDIF(G18,F18,"md")<1),DATEDIF(G18,F18,"ym") & " mois ",IF(AND(DATEDIF(G18,F18,"y")<1,DATEDIF(G18,F18,"ym")<1,DATEDIF(G18,F18,"md")>=1),DATEDIF(G18,F18,"md") & " jours ",)))))))," ") -> 0 | N18: =+NETWORKDAYS(H18,I18) -> 0 | O18: =+VLOOKUP(A18,'Salaire moyen'!B16:P65,15,FALSE) -> #N/A | P18: =+O18*L18/24 -> #N/A
A19: =+'Salaire moyen'!B17 -> 0 | L19: =IFERROR(ROUND((DATEDIF($B$2,G19,"m")+(DATEDIF($B$2,G19,"md"))/30)*2,0)+J19-K19,J19-K19) -> 0 | M19: =+IFERROR(IF(AND(DATEDIF(G19,F19,"y")>=1,DATEDIF(G19,F19,"ym")>=1,DATEDIF(G19,F19,"md")>=1),DATEDIF(G19,F19,"y") & " ans " & DATEDIF(G19,F19,"ym") & " mois " & DATEDIF(G19,F19,"md") & " jours ",IF(AND(DATEDIF(G19,F19,"y")>=1,DATEDIF(G19,F19,"ym")>=1,DATEDIF(G19,F19,"md")<1),DATEDIF(G19,F19,"y") & " ans " & DATEDIF(G19,F19,"ym") & " mois ",IF(AND(DATEDIF(G19,F19,"y")>=1,DATEDIF(G19,F19,"ym")<1,DATEDIF(G19,F19,"md")>=1),DATEDIF(G19,F19,"y") & " ans " & DATEDIF(G19,F19,"md") & " jours ",IF(AND(DATEDIF(G19,F19,"y")>=1,DATEDIF(G19,F19,"ym")<1,DATEDIF(G19,F19,"md")<1),DATEDIF(G19,F19,"y") & " ans ",IF(AND(DATEDIF(G19,F19,"y")<1,DATEDIF(G19,F19,"ym")>=1,DATEDIF(G19,F19,"md")>=1),DATEDIF(G19,F19,"ym") & " mois " & DATEDIF(G19,F19,"md") & " jours ",IF(AND(DATEDIF(G19,F19,"y")<1,DATEDIF(G19,F19,"ym")>=1,DATEDIF(G19,F19,"md")<1),DATEDIF(G19,F19,"ym") & " mois ",IF(AND(DATEDIF(G19,F19,"y")<1,DATEDIF(G19,F19,"ym")<1,DATEDIF(G19,F19,"md")>=1),DATEDIF(G19,F19,"md") & " jours ",)))))))," ") -> 0 | N19: =+NETWORKDAYS(H19,I19) -> 0 | O19: =+VLOOKUP(A19,'Salaire moyen'!B17:P66,15,FALSE) -> #N/A | P19: =+O19*L19/24 -> #N/A
... A32: =+'Salaire moyen'!B30 -> 0 | L32: =IFERROR(ROUND((DATEDIF($B$2,G32,"m")+(DATEDIF($B$2,G32,"md"))/30)*2,0)+J32-K32,J32-K32) -> 0 | M32: =+IFERROR(IF(AND(DATEDIF(G32,F32,"y")>=1,DATEDIF(G32,F32,"ym")>=1,DATEDIF(G32,F32,"md")>=1),DATEDIF(G32,F32,"y") & " ans " & DATEDIF(G32,F32,"ym") & " mois " & DATEDIF(G32,F32,"md") & " jours ",IF(AND(DATEDIF(G32,F32,"y")>=1,DATEDIF(G32,F32,"ym")>=1,DATEDIF(G32,F32,"md")<1),DATEDIF(G32,F32,"y") & " ans " & DATEDIF(G32,F32,"ym") & " mois ",IF(AND(DATEDIF(G32,F32,"y")>=1,DATEDIF(G32,F32,"ym")<1,DATEDIF(G32,F32,"md")>=1),DATEDIF(G32,F32,"y") & " ans " & DATEDIF(G32,F32,"md") & " jours ",IF(AND(DATEDIF(G32,F32,"y")>=1,DATEDIF(G32,F32,"ym")<1,DATEDIF(G32,F32,"md")<1),DATEDIF(G32,F32,"y") & " ans ",IF(AND(DATEDIF(G32,F32,"y")<1,DATEDIF(G32,F32,"ym")>=1,DATEDIF(G32,F32,"md")>=1),DATEDIF(G32,F32,"ym") & " mois " & DATEDIF(G32,F32,"md") & " jours ",IF(AND(DATEDIF(G32,F32,"y")<1,DATEDIF(G32,F32,"ym")>=1,DATEDIF(G32,F32,"md")<1),DATEDIF(G32,F32,"ym") & " mois ",IF(AND(DATEDIF(G32,F32,"y")<1,DATEDIF(G32,F32,"ym")<1,DATEDIF(G32,F32,"md")>=1),DATEDIF(G32,F32,"md") & " jours ",)))))))," ") -> 0 | N32: =+NETWORKDAYS(H32,I32) -> 0 | O32: =+VLOOKUP(A32,'Salaire moyen'!B30:P79,15,FALSE) -> #N/A | P32: =+O32*L32/24 -> #N/A
A33: =+'Salaire moyen'!B32 -> 0 | L33: =IFERROR(ROUND((DATEDIF($B$2,G33,"m")+(DATEDIF($B$2,G33,"md"))/30)*2,0)+J33-K33,J33-K33) -> 0 | M33: =+IFERROR(IF(AND(DATEDIF(G33,F33,"y")>=1,DATEDIF(G33,F33,"ym")>=1,DATEDIF(G33,F33,"md")>=1),DATEDIF(G33,F33,"y") & " ans " & DATEDIF(G33,F33,"ym") & " mois " & DATEDIF(G33,F33,"md") & " jours ",IF(AND(DATEDIF(G33,F33,"y")>=1,DATEDIF(G33,F33,"ym")>=1,DATEDIF(G33,F33,"md")<1),DATEDIF(G33,F33,"y") & " ans " & DATEDIF(G33,F33,"ym") & " mois ",IF(AND(DATEDIF(G33,F33,"y")>=1,DATEDIF(G33,F33,"ym")<1,DATEDIF(G33,F33,"md")>=1),DATEDIF(G33,F33,"y") & " ans " & DATEDIF(G33,F33,"md") & " jours ",IF(AND(DATEDIF(G33,F33,"y")>=1,DATEDIF(G33,F33,"ym")<1,DATEDIF(G33,F33,"md")<1),DATEDIF(G33,F33,"y") & " ans ",IF(AND(DATEDIF(G33,F33,"y")<1,DATEDIF(G33,F33,"ym")>=1,DATEDIF(G33,F33,"md")>=1),DATEDIF(G33,F33,"ym") & " mois " & DATEDIF(G33,F33,"md") & " jours ",IF(AND(DATEDIF(G33,F33,"y")<1,DATEDIF(G33,F33,"ym")>=1,DATEDIF(G33,F33,"md")<1),DATEDIF(G33,F33,"ym") & " mois ",IF(AND(DATEDIF(G33,F33,"y")<1,DATEDIF(G33,F33,"ym")<1,DATEDIF(G33,F33,"md")>=1),DATEDIF(G33,F33,"md") & " jours ",)))))))," ") -> 0 | N33: =+NETWORKDAYS(H33,I33) -> 0 | O33: =+VLOOKUP(A33,'Salaire moyen'!B32:P81,15,FALSE) -> #N/A | P33: =+O33*L33/24 -> #N/A
A34: =+'Salaire moyen'!B33 -> 0 | L34: =IFERROR(ROUND((DATEDIF($B$2,G34,"m")+(DATEDIF($B$2,G34,"md"))/30)*2,0)+J34-K34,J34-K34) -> 0 | M34: =+IFERROR(IF(AND(DATEDIF(G34,F34,"y")>=1,DATEDIF(G34,F34,"ym")>=1,DATEDIF(G34,F34,"md")>=1),DATEDIF(G34,F34,"y") & " ans " & DATEDIF(G34,F34,"ym") & " mois " & DATEDIF(G34,F34,"md") & " jours ",IF(AND(DATEDIF(G34,F34,"y")>=1,DATEDIF(G34,F34,"ym")>=1,DATEDIF(G34,F34,"md")<1),DATEDIF(G34,F34,"y") & " ans " & DATEDIF(G34,F34,"ym") & " mois ",IF(AND(DATEDIF(G34,F34,"y")>=1,DATEDIF(G34,F34,"ym")<1,DATEDIF(G34,F34,"md")>=1),DATEDIF(G34,F34,"y") & " ans " & DATEDIF(G34,F34,"md") & " jours ",IF(AND(DATEDIF(G34,F34,"y")>=1,DATEDIF(G34,F34,"ym")<1,DATEDIF(G34,F34,"md")<1),DATEDIF(G34,F34,"y") & " ans ",IF(AND(DATEDIF(G34,F34,"y")<1,DATEDIF(G34,F34,"ym")>=1,DATEDIF(G34,F34,"md")>=1),DATEDIF(G34,F34,"ym") & " mois " & DATEDIF(G34,F34,"md") & " jours ",IF(AND(DATEDIF(G34,F34,"y")<1,DATEDIF(G34,F34,"ym")>=1,DATEDIF(G34,F34,"md")<1),DATEDIF(G34,F34,"ym") & " mois ",IF(AND(DATEDIF(G34,F34,"y")<1,DATEDIF(G34,F34,"ym")<1,DATEDIF(G34,F34,"md")>=1),DATEDIF(G34,F34,"md") & " jours ",)))))))," ") -> 0 | N34: =+NETWORKDAYS(H34,I34) -> 0 | O34: =+VLOOKUP(A34,'Salaire moyen'!B33:P82,15,FALSE) -> #N/A | P34: =+O34*L34/24 -> #N/A
A35: =+'Salaire moyen'!B34 -> 0 | L35: =IFERROR(ROUND((DATEDIF($B$2,G35,"m")+(DATEDIF($B$2,G35,"md"))/30)*2,0)+J35-K35,J35-K35) -> 0 | M35: =+IFERROR(IF(AND(DATEDIF(G35,F35,"y")>=1,DATEDIF(G35,F35,"ym")>=1,DATEDIF(G35,F35,"md")>=1),DATEDIF(G35,F35,"y") & " ans " & DATEDIF(G35,F35,"ym") & " mois " & DATEDIF(G35,F35,"md") & " jours ",IF(AND(DATEDIF(G35,F35,"y")>=1,DATEDIF(G35,F35,"ym")>=1,DATEDIF(G35,F35,"md")<1),DATEDIF(G35,F35,"y") & " ans " & DATEDIF(G35,F35,"ym") & " mois ",IF(AND(DATEDIF(G35,F35,"y")>=1,DATEDIF(G35,F35,"ym")<1,DATEDIF(G35,F35,"md")>=1),DATEDIF(G35,F35,"y") & " ans " & DATEDIF(G35,F35,"md") & " jours ",IF(AND(DATEDIF(G35,F35,"y")>=1,DATEDIF(G35,F35,"ym")<1,DATEDIF(G35,F35,"md")<1),DATEDIF(G35,F35,"y") & " ans ",IF(AND(DATEDIF(G35,F35,"y")<1,DATEDIF(G35,F35,"ym")>=1,DATEDIF(G35,F35,"md")>=1),DATEDIF(G35,F35,"ym") & " mois " & DATEDIF(G35,F35,"md") & " jours ",IF(AND(DATEDIF(G35,F35,"y")<1,DATEDIF(G35,F35,"ym")>=1,DATEDIF(G35,F35,"md")<1),DATEDIF(G35,F35,"ym") & " mois ",IF(AND(DATEDIF(G35,F35,"y")<1,DATEDIF(G35,F35,"ym")<1,DATEDIF(G35,F35,"md")>=1),DATEDIF(G35,F35,"md") & " jours ",)))))))," ") -> 0 | N35: =+NETWORKDAYS(H35,I35) -> 0 | O35: =+VLOOKUP(A35,'Salaire moyen'!B34:P83,15,FALSE) -> #N/A | P35: =+O35*L35/24 -> #N/A
A36: =+'Salaire moyen'!B35 -> 0 | L36: =IFERROR(ROUND((DATEDIF($B$2,G36,"m")+(DATEDIF($B$2,G36,"md"))/30)*2,0)+J36-K36,J36-K36) -> 0 | M36: =+IFERROR(IF(AND(DATEDIF(G36,F36,"y")>=1,DATEDIF(G36,F36,"ym")>=1,DATEDIF(G36,F36,"md")>=1),DATEDIF(G36,F36,"y") & " ans " & DATEDIF(G36,F36,"ym") & " mois " & DATEDIF(G36,F36,"md") & " jours ",IF(AND(DATEDIF(G36,F36,"y")>=1,DATEDIF(G36,F36,"ym")>=1,DATEDIF(G36,F36,"md")<1),DATEDIF(G36,F36,"y") & " ans " & DATEDIF(G36,F36,"ym") & " mois ",IF(AND(DATEDIF(G36,F36,"y")>=1,DATEDIF(G36,F36,"ym")<1,DATEDIF(G36,F36,"md")>=1),DATEDIF(G36,F36,"y") & " ans " & DATEDIF(G36,F36,"md") & " jours ",IF(AND(DATEDIF(G36,F36,"y")>=1,DATEDIF(G36,F36,"ym")<1,DATEDIF(G36,F36,"md")<1),DATEDIF(G36,F36,"y") & " ans ",IF(AND(DATEDIF(G36,F36,"y")<1,DATEDIF(G36,F36,"ym")>=1,DATEDIF(G36,F36,"md")>=1),DATEDIF(G36,F36,"ym") & " mois " & DATEDIF(G36,F36,"md") & " jours ",IF(AND(DATEDIF(G36,F36,"y")<1,DATEDIF(G36,F36,"ym")>=1,DATEDIF(G36,F36,"md")<1),DATEDIF(G36,F36,"ym") & " mois ",IF(AND(DATEDIF(G36,F36,"y")<1,DATEDIF(G36,F36,"ym")<1,DATEDIF(G36,F36,"md")>=1),DATEDIF(G36,F36,"md") & " jours ",)))))))," ") -> 0 | N36: =+NETWORKDAYS(H36,I36) -> 0 | O36: =+VLOOKUP(A36,'Salaire moyen'!B35:P84,15,FALSE) -> #N/A | P36: =+O36*L36/24 -> #N/A
A37: =+'Salaire moyen'!B36 -> 0 | L37: =IFERROR(ROUND((DATEDIF($B$2,G37,"m")+(DATEDIF($B$2,G37,"md"))/30)*2,0)+J37-K37,J37-K37) -> 0 | M37: =+IFERROR(IF(AND(DATEDIF(G37,F37,"y")>=1,DATEDIF(G37,F37,"ym")>=1,DATEDIF(G37,F37,"md")>=1),DATEDIF(G37,F37,"y") & " ans " & DATEDIF(G37,F37,"ym") & " mois " & DATEDIF(G37,F37,"md") & " jours ",IF(AND(DATEDIF(G37,F37,"y")>=1,DATEDIF(G37,F37,"ym")>=1,DATEDIF(G37,F37,"md")<1),DATEDIF(G37,F37,"y") & " ans " & DATEDIF(G37,F37,"ym") & " mois ",IF(AND(DATEDIF(G37,F37,"y")>=1,DATEDIF(G37,F37,"ym")<1,DATEDIF(G37,F37,"md")>=1),DATEDIF(G37,F37,"y") & " ans " & DATEDIF(G37,F37,"md") & " jours ",IF(AND(DATEDIF(G37,F37,"y")>=1,DATEDIF(G37,F37,"ym")<1,DATEDIF(G37,F37,"md")<1),DATEDIF(G37,F37,"y") & " ans ",IF(AND(DATEDIF(G37,F37,"y")<1,DATEDIF(G37,F37,"ym")>=1,DATEDIF(G37,F37,"md")>=1),DATEDIF(G37,F37,"ym") & " mois " & DATEDIF(G37,F37,"md") & " jours ",IF(AND(DATEDIF(G37,F37,"y")<1,DATEDIF(G37,F37,"ym")>=1,DATEDIF(G37,F37,"md")<1),DATEDIF(G37,F37,"ym") & " mois ",IF(AND(DATEDIF(G37,F37,"y")<1,DATEDIF(G37,F37,"ym")<1,DATEDIF(G37,F37,"md")>=1),DATEDIF(G37,F37,"md") & " jours ",)))))))," ") -> 0 | N37: =+NETWORKDAYS(H37,I37) -> 0 | O37: =+VLOOKUP(A37,'Salaire moyen'!B36:P85,15,FALSE) -> #N/A | P37: =+O37*L37/24 -> #N/A
A38: =+'Salaire moyen'!B37 -> 0 | L38: =IFERROR(ROUND((DATEDIF($B$2,G38,"m")+(DATEDIF($B$2,G38,"md"))/30)*2,0)+J38-K38,J38-K38) -> 0 | M38: =+IFERROR(IF(AND(DATEDIF(G38,F38,"y")>=1,DATEDIF(G38,F38,"ym")>=1,DATEDIF(G38,F38,"md")>=1),DATEDIF(G38,F38,"y") & " ans " & DATEDIF(G38,F38,"ym") & " mois " & DATEDIF(G38,F38,"md") & " jours ",IF(AND(DATEDIF(G38,F38,"y")>=1,DATEDIF(G38,F38,"ym")>=1,DATEDIF(G38,F38,"md")<1),DATEDIF(G38,F38,"y") & " ans " & DATEDIF(G38,F38,"ym") & " mois ",IF(AND(DATEDIF(G38,F38,"y")>=1,DATEDIF(G38,F38,"ym")<1,DATEDIF(G38,F38,"md")>=1),DATEDIF(G38,F38,"y") & " ans " & DATEDIF(G38,F38,"md") & " jours ",IF(AND(DATEDIF(G38,F38,"y")>=1,DATEDIF(G38,F38,"ym")<1,DATEDIF(G38,F38,"md")<1),DATEDIF(G38,F38,"y") & " ans ",IF(AND(DATEDIF(G38,F38,"y")<1,DATEDIF(G38,F38,"ym")>=1,DATEDIF(G38,F38,"md")>=1),DATEDIF(G38,F38,"ym") & " mois " & DATEDIF(G38,F38,"md") & " jours ",IF(AND(DATEDIF(G38,F38,"y")<1,DATEDIF(G38,F38,"ym")>=1,DATEDIF(G38,F38,"md")<1),DATEDIF(G38,F38,"ym") & " mois ",IF(AND(DATEDIF(G38,F38,"y")<1,DATEDIF(G38,F38,"ym")<1,DATEDIF(G38,F38,"md")>=1),DATEDIF(G38,F38,"md") & " jours ",)))))))," ") -> 0 | N38: =+NETWORKDAYS(H38,I38) -> 0 | O38: =+VLOOKUP(A38,'Salaire moyen'!B37:P86,15,FALSE) -> #N/A | P38: =+O38*L38/24 -> #N/A
A39: =+'Salaire moyen'!B38 -> 0 | L39: =IFERROR(ROUND((DATEDIF($B$2,G39,"m")+(DATEDIF($B$2,G39,"md"))/30)*2,0)+J39-K39,J39-K39) -> 0 | M39: =+IFERROR(IF(AND(DATEDIF(G39,F39,"y")>=1,DATEDIF(G39,F39,"ym")>=1,DATEDIF(G39,F39,"md")>=1),DATEDIF(G39,F39,"y") & " ans " & DATEDIF(G39,F39,"ym") & " mois " & DATEDIF(G39,F39,"md") & " jours ",IF(AND(DATEDIF(G39,F39,"y")>=1,DATEDIF(G39,F39,"ym")>=1,DATEDIF(G39,F39,"md")<1),DATEDIF(G39,F39,"y") & " ans " & DATEDIF(G39,F39,"ym") & " mois ",IF(AND(DATEDIF(G39,F39,"y")>=1,DATEDIF(G39,F39,"ym")<1,DATEDIF(G39,F39,"md")>=1),DATEDIF(G39,F39,"y") & " ans " & DATEDIF(G39,F39,"md") & " jours ",IF(AND(DATEDIF(G39,F39,"y")>=1,DATEDIF(G39,F39,"ym")<1,DATEDIF(G39,F39,"md")<1),DATEDIF(G39,F39,"y") & " ans ",IF(AND(DATEDIF(G39,F39,"y")<1,DATEDIF(G39,F39,"ym")>=1,DATEDIF(G39,F39,"md")>=1),DATEDIF(G39,F39,"ym") & " mois " & DATEDIF(G39,F39,"md") & " jours ",IF(AND(DATEDIF(G39,F39,"y")<1,DATEDIF(G39,F39,"ym")>=1,DATEDIF(G39,F39,"md")<1),DATEDIF(G39,F39,"ym") & " mois ",IF(AND(DATEDIF(G39,F39,"y")<1,DATEDIF(G39,F39,"ym")<1,DATEDIF(G39,F39,"md")>=1),DATEDIF(G39,F39,"md") & " jours ",)))))))," ") -> 0 | N39: =+NETWORKDAYS(H39,I39) -> 0 | O39: =+VLOOKUP(A39,'Salaire moyen'!B38:P87,15,FALSE) -> #N/A | P39: =+O39*L39/24 -> #N/A
A40: =+'Salaire moyen'!B39 -> 0 | L40: =IFERROR(ROUND((DATEDIF($B$2,G40,"m")+(DATEDIF($B$2,G40,"md"))/30)*2,0)+J40-K40,J40-K40) -> 0 | M40: =+IFERROR(IF(AND(DATEDIF(G40,F40,"y")>=1,DATEDIF(G40,F40,"ym")>=1,DATEDIF(G40,F40,"md")>=1),DATEDIF(G40,F40,"y") & " ans " & DATEDIF(G40,F40,"ym") & " mois " & DATEDIF(G40,F40,"md") & " jours ",IF(AND(DATEDIF(G40,F40,"y")>=1,DATEDIF(G40,F40,"ym")>=1,DATEDIF(G40,F40,"md")<1),DATEDIF(G40,F40,"y") & " ans " & DATEDIF(G40,F40,"ym") & " mois ",IF(AND(DATEDIF(G40,F40,"y")>=1,DATEDIF(G40,F40,"ym")<1,DATEDIF(G40,F40,"md")>=1),DATEDIF(G40,F40,"y") & " ans " & DATEDIF(G40,F40,"md") & " jours ",IF(AND(DATEDIF(G40,F40,"y")>=1,DATEDIF(G40,F40,"ym")<1,DATEDIF(G40,F40,"md")<1),DATEDIF(G40,F40,"y") & " ans ",IF(AND(DATEDIF(G40,F40,"y")<1,DATEDIF(G40,F40,"ym")>=1,DATEDIF(G40,F40,"md")>=1),DATEDIF(G40,F40,"ym") & " mois " & DATEDIF(G40,F40,"md") & " jours ",IF(AND(DATEDIF(G40,F40,"y")<1,DATEDIF(G40,F40,"ym")>=1,DATEDIF(G40,F40,"md")<1),DATEDIF(G40,F40,"ym") & " mois ",IF(AND(DATEDIF(G40,F40,"y")<1,DATEDIF(G40,F40,"ym")<1,DATEDIF(G40,F40,"md")>=1),DATEDIF(G40,F40,"md") & " jours ",)))))))," ") -> 0 | N40: =+NETWORKDAYS(H40,I40) -> 0 | O40: =+VLOOKUP(A40,'Salaire moyen'!B39:P88,15,FALSE) -> #N/A | P40: =+O40*L40/24 -> #N/A
A41: =+'Salaire moyen'!B40 -> 0 | L41: =IFERROR(ROUND((DATEDIF($B$2,G41,"m")+(DATEDIF($B$2,G41,"md"))/30)*2,0)+J41-K41,J41-K41) -> 0 | M41: =+IFERROR(IF(AND(DATEDIF(G41,F41,"y")>=1,DATEDIF(G41,F41,"ym")>=1,DATEDIF(G41,F41,"md")>=1),DATEDIF(G41,F41,"y") & " ans " & DATEDIF(G41,F41,"ym") & " mois " & DATEDIF(G41,F41,"md") & " jours ",IF(AND(DATEDIF(G41,F41,"y")>=1,DATEDIF(G41,F41,"ym")>=1,DATEDIF(G41,F41,"md")<1),DATEDIF(G41,F41,"y") & " ans " & DATEDIF(G41,F41,"ym") & " mois ",IF(AND(DATEDIF(G41,F41,"y")>=1,DATEDIF(G41,F41,"ym")<1,DATEDIF(G41,F41,"md")>=1),DATEDIF(G41,F41,"y") & " ans " & DATEDIF(G41,F41,"md") & " jours ",IF(AND(DATEDIF(G41,F41,"y")>=1,DATEDIF(G41,F41,"ym")<1,DATEDIF(G41,F41,"md")<1),DATEDIF(G41,F41,"y") & " ans ",IF(AND(DATEDIF(G41,F41,"y")<1,DATEDIF(G41,F41,"ym")>=1,DATEDIF(G41,F41,"md")>=1),DATEDIF(G41,F41,"ym") & " mois " & DATEDIF(G41,F41,"md") & " jours ",IF(AND(DATEDIF(G41,F41,"y")<1,DATEDIF(G41,F41,"ym")>=1,DATEDIF(G41,F41,"md")<1),DATEDIF(G41,F41,"ym") & " mois ",IF(AND(DATEDIF(G41,F41,"y")<1,DATEDIF(G41,F41,"ym")<1,DATEDIF(G41,F41,"md")>=1),DATEDIF(G41,F41,"md") & " jours ",)))))))," ") -> 0 | N41: =+NETWORKDAYS(H41,I41) -> 0 | O41: =+VLOOKUP(A41,'Salaire moyen'!B40:P89,15,FALSE) -> #N/A | P41: =+O41*L41/24 -> #N/A
A42: =+'Salaire moyen'!B41 -> 0 | L42: =IFERROR(ROUND((DATEDIF($B$2,G42,"m")+(DATEDIF($B$2,G42,"md"))/30)*2,0)+J42-K42,J42-K42) -> 0 | M42: =+IFERROR(IF(AND(DATEDIF(G42,F42,"y")>=1,DATEDIF(G42,F42,"ym")>=1,DATEDIF(G42,F42,"md")>=1),DATEDIF(G42,F42,"y") & " ans " & DATEDIF(G42,F42,"ym") & " mois " & DATEDIF(G42,F42,"md") & " jours ",IF(AND(DATEDIF(G42,F42,"y")>=1,DATEDIF(G42,F42,"ym")>=1,DATEDIF(G42,F42,"md")<1),DATEDIF(G42,F42,"y") & " ans " & DATEDIF(G42,F42,"ym") & " mois ",IF(AND(DATEDIF(G42,F42,"y")>=1,DATEDIF(G42,F42,"ym")<1,DATEDIF(G42,F42,"md")>=1),DATEDIF(G42,F42,"y") & " ans " & DATEDIF(G42,F42,"md") & " jours ",IF(AND(DATEDIF(G42,F42,"y")>=1,DATEDIF(G42,F42,"ym")<1,DATEDIF(G42,F42,"md")<1),DATEDIF(G42,F42,"y") & " ans ",IF(AND(DATEDIF(G42,F42,"y")<1,DATEDIF(G42,F42,"ym")>=1,DATEDIF(G42,F42,"md")>=1),DATEDIF(G42,F42,"ym") & " mois " & DATEDIF(G42,F42,"md") & " jours ",IF(AND(DATEDIF(G42,F42,"y")<1,DATEDIF(G42,F42,"ym")>=1,DATEDIF(G42,F42,"md")<1),DATEDIF(G42,F42,"ym") & " mois ",IF(AND(DATEDIF(G42,F42,"y")<1,DATEDIF(G42,F42,"ym")<1,DATEDIF(G42,F42,"md")>=1),DATEDIF(G42,F42,"md") & " jours ",)))))))," ") -> 0 | N42: =+NETWORKDAYS(H42,I42) -> 0 | O42: =+VLOOKUP(A42,'Salaire moyen'!B41:P90,15,FALSE) -> #N/A | P42: =+O42*L42/24 -> #N/A
A43: =+'Salaire moyen'!B42 -> 0 | L43: =IFERROR(ROUND((DATEDIF($B$2,G43,"m")+(DATEDIF($B$2,G43,"md"))/30)*2,0)+J43-K43,J43-K43) -> 0 | M43: =+IFERROR(IF(AND(DATEDIF(G43,F43,"y")>=1,DATEDIF(G43,F43,"ym")>=1,DATEDIF(G43,F43,"md")>=1),DATEDIF(G43,F43,"y") & " ans " & DATEDIF(G43,F43,"ym") & " mois " & DATEDIF(G43,F43,"md") & " jours ",IF(AND(DATEDIF(G43,F43,"y")>=1,DATEDIF(G43,F43,"ym")>=1,DATEDIF(G43,F43,"md")<1),DATEDIF(G43,F43,"y") & " ans " & DATEDIF(G43,F43,"ym") & " mois ",IF(AND(DATEDIF(G43,F43,"y")>=1,DATEDIF(G43,F43,"ym")<1,DATEDIF(G43,F43,"md")>=1),DATEDIF(G43,F43,"y") & " ans " & DATEDIF(G43,F43,"md") & " jours ",IF(AND(DATEDIF(G43,F43,"y")>=1,DATEDIF(G43,F43,"ym")<1,DATEDIF(G43,F43,"md")<1),DATEDIF(G43,F43,"y") & " ans ",IF(AND(DATEDIF(G43,F43,"y")<1,DATEDIF(G43,F43,"ym")>=1,DATEDIF(G43,F43,"md")>=1),DATEDIF(G43,F43,"ym") & " mois " & DATEDIF(G43,F43,"md") & " jours ",IF(AND(DATEDIF(G43,F43,"y")<1,DATEDIF(G43,F43,"ym")>=1,DATEDIF(G43,F43,"md")<1),DATEDIF(G43,F43,"ym") & " mois ",IF(AND(DATEDIF(G43,F43,"y")<1,DATEDIF(G43,F43,"ym")<1,DATEDIF(G43,F43,"md")>=1),DATEDIF(G43,F43,"md") & " jours ",)))))))," ") -> 0 | N43: =+NETWORKDAYS(H43,I43) -> 0 | O43: =+VLOOKUP(A43,'Salaire moyen'!B42:P91,15,FALSE) -> #N/A | P43: =+O43*L43/24 -> #N/A
A44: =+'Salaire moyen'!B43 -> 0 | L44: =IFERROR(ROUND((DATEDIF($B$2,G44,"m")+(DATEDIF($B$2,G44,"md"))/30)*2,0)+J44-K44,J44-K44) -> 0 | M44: =+IFERROR(IF(AND(DATEDIF(G44,F44,"y")>=1,DATEDIF(G44,F44,"ym")>=1,DATEDIF(G44,F44,"md")>=1),DATEDIF(G44,F44,"y") & " ans " & DATEDIF(G44,F44,"ym") & " mois " & DATEDIF(G44,F44,"md") & " jours ",IF(AND(DATEDIF(G44,F44,"y")>=1,DATEDIF(G44,F44,"ym")>=1,DATEDIF(G44,F44,"md")<1),DATEDIF(G44,F44,"y") & " ans " & DATEDIF(G44,F44,"ym") & " mois ",IF(AND(DATEDIF(G44,F44,"y")>=1,DATEDIF(G44,F44,"ym")<1,DATEDIF(G44,F44,"md")>=1),DATEDIF(G44,F44,"y") & " ans " & DATEDIF(G44,F44,"md") & " jours ",IF(AND(DATEDIF(G44,F44,"y")>=1,DATEDIF(G44,F44,"ym")<1,DATEDIF(G44,F44,"md")<1),DATEDIF(G44,F44,"y") & " ans ",IF(AND(DATEDIF(G44,F44,"y")<1,DATEDIF(G44,F44,"ym")>=1,DATEDIF(G44,F44,"md")>=1),DATEDIF(G44,F44,"ym") & " mois " & DATEDIF(G44,F44,"md") & " jours ",IF(AND(DATEDIF(G44,F44,"y")<1,DATEDIF(G44,F44,"ym")>=1,DATEDIF(G44,F44,"md")<1),DATEDIF(G44,F44,"ym") & " mois ",IF(AND(DATEDIF(G44,F44,"y")<1,DATEDIF(G44,F44,"ym")<1,DATEDIF(G44,F44,"md")>=1),DATEDIF(G44,F44,"md") & " jours ",)))))))," ") -> 0 | N44: =+NETWORKDAYS(H44,I44) -> 0 | O44: =+VLOOKUP(A44,'Salaire moyen'!B43:P92,15,FALSE) -> #N/A | P44: =+O44*L44/24 -> #N/A
... A46: =+'Salaire moyen'!B45 -> 0 | L46: =IFERROR(ROUND((DATEDIF($B$2,G46,"m")+(DATEDIF($B$2,G46,"md"))/30)*2,0)+J46-K46,J46-K46) -> 0 | M46: =+IFERROR(IF(AND(DATEDIF(G46,F46,"y")>=1,DATEDIF(G46,F46,"ym")>=1,DATEDIF(G46,F46,"md")>=1),DATEDIF(G46,F46,"y") & " ans " & DATEDIF(G46,F46,"ym") & " mois " & DATEDIF(G46,F46,"md") & " jours ",IF(AND(DATEDIF(G46,F46,"y")>=1,DATEDIF(G46,F46,"ym")>=1,DATEDIF(G46,F46,"md")<1),DATEDIF(G46,F46,"y") & " ans " & DATEDIF(G46,F46,"ym") & " mois ",IF(AND(DATEDIF(G46,F46,"y")>=1,DATEDIF(G46,F46,"ym")<1,DATEDIF(G46,F46,"md")>=1),DATEDIF(G46,F46,"y") & " ans " & DATEDIF(G46,F46,"md") & " jours ",IF(AND(DATEDIF(G46,F46,"y")>=1,DATEDIF(G46,F46,"ym")<1,DATEDIF(G46,F46,"md")<1),DATEDIF(G46,F46,"y") & " ans ",IF(AND(DATEDIF(G46,F46,"y")<1,DATEDIF(G46,F46,"ym")>=1,DATEDIF(G46,F46,"md")>=1),DATEDIF(G46,F46,"ym") & " mois " & DATEDIF(G46,F46,"md") & " jours ",IF(AND(DATEDIF(G46,F46,"y")<1,DATEDIF(G46,F46,"ym")>=1,DATEDIF(G46,F46,"md")<1),DATEDIF(G46,F46,"ym") & " mois ",IF(AND(DATEDIF(G46,F46,"y")<1,DATEDIF(G46,F46,"ym")<1,DATEDIF(G46,F46,"md")>=1),DATEDIF(G46,F46,"md") & " jours ",)))))))," ") -> 0 | N46: =+NETWORKDAYS(H46,I46) -> 0 | O46: =+VLOOKUP(A46,'Salaire moyen'!B45:P94,15,FALSE) -> #N/A | P46: =+O46*L46/24 -> #N/A

Sheet Nette allocat°
H2: Rémunérations perçues au cours du mois de démissions | J2: Charges ouvrières | L2: Retenues à effectuer ou Salaire à payer | O2: Charges patronales | R2: Détails masse salariale mars 2022
A3: Noms et Prénoms | B3: Sal. Brut des 12 mois précédents | C3: Treizième mois | D3: Rémunérations assimilées au 13 ème mois | E3: Total Global | F3: Salaire moyen | G3: ITS Moyen | H3: Paie mensuelle (mois de démission) | I3: Rémunérations exceptionnelles (mois de démissions) | J3: ITS à retenir | K3: CNSS ouvrière | L3: Période restante due ou Préavis à payer | M3: Préjudice/Autres retenues | N3: Net à payer (Solde de tout compte) | O3: CNSS patronale | P3: VPS | Q3: Masse salariale | R3: Salaire Brut | S3: CNSS patronale | T3: VPS | U3: Masse salariale | V3: Masse salariale totale (solde tt cpte + salaire mars 2022)
A4: =+'Brute allocat°'!A7 -> 0 | B4: =+VLOOKUP(A4,'Salaire moyen'!$B$5:$O$43,14,FALSE) -> #N/A | E4: =+B4+C4+D4 -> #N/A | F4: =+E4/VLOOKUP(A4,'Salaire moyen'!$B$5:$Q$43,16,FALSE) -> #N/A | G4: =+IF(F4<=60000,0,IF(AND(F4>60000,F4<=150000),(INT(F4/1000)*1000-60000)*10%,IF(AND(F4>150000,F4<=250000),(INT(F4/1000)*1000-150000)*15%+9000,IF(AND(F4>250000,F4<=500000),(INT(F4/1000)*1000-250000)*19%+24000,IF(F4>500000,(INT(F4/1000)*1000-500000)*30%+71500))))) -> #N/A | I4: =+'Brute allocat°'!P7 -> #N/A | J4: =+((H4+I4)/F4)*G4 -> #N/A | K4: =+'Brute allocat°'!P7*3.6% -> #N/A | L4: =+IF(AND('Brute allocat°'!D7=Base!$C$3,'Brute allocat°'!B7=Base!$A$3),('Brute allocat°'!E7/(173.333333333333))*(NETWORKDAYS('Brute allocat°'!G7,'Brute allocat°'!F7)*8),IF(AND('Brute allocat°'!D7=Base!$C$3,'Brute allocat°'!B7=Base!$A$4,'Brute allocat°'!C7=Base!$B$5),'Brute allocat°'!E7,IF(AND('Brute allocat°'!D7=Base!$C$3,'Brute allocat°'!B7=Base!$A$4,'Brute allocat°'!C7=Base!$B$4),'Brute allocat°'!E7*3,IF(AND('Brute allocat°'!D7=Base!$C$5,'Brute allocat°'!B7=Base!$A$3),('Brute allocat°'!E7/(173.333333333333))*NETWORKDAYS('Brute allocat°'!G7,'Brute allocat°'!F7)*(-8),IF(AND('Brute allocat°'!D7=Base!$C$5,'Brute allocat°'!B7=Base!$A$4,'Brute allocat°'!C7=Base!$B$5),'Brute allocat°'!E7*(-1),IF(AND('Brute allocat°'!D7=Base!$C$5,'Brute allocat°'!C7=Base!$B$4),'Brute allocat°'!E7*(-3),0)))))) -> -203962.8 | N4: =+'Brute allocat°'!P7-'Nette allocat°'!J4-'Nette allocat°'!K4+L4+M4 -> #N/A | O4: =+'Brute allocat°'!P7*17.4% -> #N/A | P4: =+'Brute allocat°'!P7*4% -> #N/A | Q4: =+'Brute allocat°'!P7+'Nette allocat°'!O4+'Nette allocat°'!P4 -> #N/A | R4: 185266 | S4: =+R4*0.174 -> 32236.284 | T4: =+R4*0.04 -> 7410.64 | U4: =+R4*1.214 -> 224912.92 | V4: =+Q4+U4 -> #N/A
A5: =+'Brute allocat°'!A8 -> 0 | B5: =+VLOOKUP(A5,'Salaire moyen'!$B$5:$O$43,14,FALSE) -> #N/A | E5: =+B5+C5+D5 -> #N/A | F5: =+E5/VLOOKUP(A5,'Salaire moyen'!$B$5:$Q$43,16,FALSE) -> #N/A | G5: =+IF(F5<=60000,0,IF(AND(F5>60000,F5<=150000),(INT(F5/1000)*1000-60000)*10%,IF(AND(F5>150000,F5<=250000),(INT(F5/1000)*1000-150000)*15%+9000,IF(AND(F5>250000,F5<=500000),(INT(F5/1000)*1000-250000)*19%+24000,IF(F5>500000,(INT(F5/1000)*1000-500000)*30%+71500))))) -> #N/A | I5: =+'Brute allocat°'!P8 -> #N/A | J5: =+((H4+I5)/F5)*G5 -> #N/A | K5: =+'Brute allocat°'!P8*3.6% -> #N/A | L5: =+IF(AND('Brute allocat°'!D8=Base!$C$3,'Brute allocat°'!B8=Base!$A$3),('Brute allocat°'!E8/(173.333333333333))*(NETWORKDAYS('Brute allocat°'!G8,'Brute allocat°'!F8)*8),IF(AND('Brute allocat°'!D8=Base!$C$3,'Brute allocat°'!B8=Base!$A$4,'Brute allocat°'!C8=Base!$B$5),'Brute allocat°'!E8,IF(AND('Brute allocat°'!D8=Base!$C$3,'Brute allocat°'!B8=Base!$A$4,'Brute allocat°'!C8=Base!$B$4),'Brute allocat°'!E8*3,IF(AND('Brute allocat°'!D8=Base!$C$5,'Brute allocat°'!B8=Base!$A$3),('Brute allocat°'!E8/(173.333333333333))*NETWORKDAYS('Brute allocat°'!G8,'Brute allocat°'!F8)*(-8),IF(AND('Brute allocat°'!D8=Base!$C$5,'Brute allocat°'!B8=Base!$A$4,'Brute allocat°'!C8=Base!$B$5),'Brute allocat°'!E8*(-1),IF(AND('Brute allocat°'!D8=Base!$C$5,'Brute allocat°'!C8=Base!$B$4),'Brute allocat°'!E8*(-3),0)))))) -> 0 | N5: =+'Brute allocat°'!P8-'Nette allocat°'!J5-'Nette allocat°'!K5+L5+M5 -> #N/A | O5: =+'Brute allocat°'!P8*17.4% -> #N/A | P5: =+'Brute allocat°'!P8*4% -> #N/A | Q5: =+'Brute allocat°'!P8+'Nette allocat°'!O5+'Nette allocat°'!P5 -> #N/A | R5: 183567 | S5: =+R5*0.174 -> 31940.658 | T5: =+R5*0.04 -> 7342.68 | U5: =+R5*1.214 -> 222850.34 | V5: =+Q5+U5 -> #N/A
A6: =+'Brute allocat°'!A9 -> 0 | B6: =+VLOOKUP(A6,'Salaire moyen'!$B$5:$O$43,14,FALSE) -> #N/A | E6: =+B6+C6+D6 -> #N/A | F6: =+E6/VLOOKUP(A6,'Salaire moyen'!$B$5:$Q$43,16,FALSE) -> #N/A | G6: =+IF(F6<=60000,0,IF(AND(F6>60000,F6<=150000),(INT(F6/1000)*1000-60000)*10%,IF(AND(F6>150000,F6<=250000),(INT(F6/1000)*1000-150000)*15%+9000,IF(AND(F6>250000,F6<=500000),(INT(F6/1000)*1000-250000)*19%+24000,IF(F6>500000,(INT(F6/1000)*1000-500000)*30%+71500))))) -> #N/A | I6: =+'Brute allocat°'!P9 -> #N/A | J6: =+((H5+I6)/F6)*G6 -> #N/A | K6: =+'Brute allocat°'!P9*3.6% -> #N/A | L6: =+IF(AND('Brute allocat°'!D9=Base!$C$3,'Brute allocat°'!B9=Base!$A$3),('Brute allocat°'!E9/(173.333333333333))*(NETWORKDAYS('Brute allocat°'!G9,'Brute allocat°'!F9)*8),IF(AND('Brute allocat°'!D9=Base!$C$3,'Brute allocat°'!B9=Base!$A$4,'Brute allocat°'!C9=Base!$B$5),'Brute allocat°'!E9,IF(AND('Brute allocat°'!D9=Base!$C$3,'Brute allocat°'!B9=Base!$A$4,'Brute allocat°'!C9=Base!$B$4),'Brute allocat°'!E9*3,IF(AND('Brute allocat°'!D9=Base!$C$5,'Brute allocat°'!B9=Base!$A$3),('Brute allocat°'!E9/(173.333333333333))*NETWORKDAYS('Brute allocat°'!G9,'Brute allocat°'!F9)*(-8),IF(AND('Brute allocat°'!D9=Base!$C$5,'Brute allocat°'!B9=Base!$A$4,'Brute allocat°'!C9=Base!$B$5),'Brute allocat°'!E9*(-1),IF(AND('Brute allocat°'!D9=Base!$C$5,'Brute allocat°'!C9=Base!$B$4),'Brute allocat°'!E9*(-3),0)))))) -> 0 | N6: =+'Brute allocat°'!P9-'Nette allocat°'!J6-'Nette allocat°'!K6+L6+M6 -> #N/A | O6: =+'Brute allocat°'!P9*17.4% -> #N/A | P6: =+'Brute allocat°'!P9*4% -> #N/A | Q6: =+'Brute allocat°'!P9+'Nette allocat°'!O6+'Nette allocat°'!P6 -> #N/A
A7: =+'Brute allocat°'!A10 -> 0 | B7: =+VLOOKUP(A7,'Salaire moyen'!$B$5:$O$43,14,FALSE) -> #N/A | E7: =+B7+C7+D7 -> #N/A | F7: =+E7/VLOOKUP(A7,'Salaire moyen'!$B$5:$Q$43,16,FALSE) -> #N/A | G7: =+IF(F7<=60000,0,IF(AND(F7>60000,F7<=150000),(INT(F7/1000)*1000-60000)*10%,IF(AND(F7>150000,F7<=250000),(INT(F7/1000)*1000-150000)*15%+9000,IF(AND(F7>250000,F7<=500000),(INT(F7/1000)*1000-250000)*19%+24000,IF(F7>500000,(INT(F7/1000)*1000-500000)*30%+71500))))) -> #N/A | I7: =+'Brute allocat°'!P10 -> #N/A | J7: =+((H6+I7)/F7)*G7 -> #N/A | K7: =+'Brute allocat°'!P10*3.6% -> #N/A | L7: =+IF(AND('Brute allocat°'!D10=Base!$C$3,'Brute allocat°'!B10=Base!$A$3),('Brute allocat°'!E10/(173.333333333333))*(NETWORKDAYS('Brute allocat°'!G10,'Brute allocat°'!F10)*8),IF(AND('Brute allocat°'!D10=Base!$C$3,'Brute allocat°'!B10=Base!$A$4,'Brute allocat°'!C10=Base!$B$5),'Brute allocat°'!E10,IF(AND('Brute allocat°'!D10=Base!$C$3,'Brute allocat°'!B10=Base!$A$4,'Brute allocat°'!C10=Base!$B$4),'Brute allocat°'!E10*3,IF(AND('Brute allocat°'!D10=Base!$C$5,'Brute allocat°'!B10=Base!$A$3),('Brute allocat°'!E10/(173.333333333333))*NETWORKDAYS('Brute allocat°'!G10,'Brute allocat°'!F10)*(-8),IF(AND('Brute allocat°'!D10=Base!$C$5,'Brute allocat°'!B10=Base!$A$4,'Brute allocat°'!C10=Base!$B$5),'Brute allocat°'!E10*(-1),IF(AND('Brute allocat°'!D10=Base!$C$5,'Brute allocat°'!C10=Base!$B$4),'Brute allocat°'!E10*(-3),0)))))) -> 0 | N7: =+'Brute allocat°'!P10-'Nette allocat°'!J7-'Nette allocat°'!K7+L7+M7 -> #N/A | O7: =+'Brute allocat°'!P10*17.4% -> #N/A | P7: =+'Brute allocat°'!P10*4% -> #N/A | Q7: =+'Brute allocat°'!P10+'Nette allocat°'!O7+'Nette allocat°'!P7 -> #N/A
A8: =+'Brute allocat°'!A11 -> 0 | B8: =+VLOOKUP(A8,'Salaire moyen'!$B$5:$O$43,14,FALSE) -> #N/A | E8: =+B8+C8+D8 -> #N/A | F8: =+E8/VLOOKUP(A8,'Salaire moyen'!$B$5:$Q$43,16,FALSE) -> #N/A | G8: =+IF(F8<=60000,0,IF(AND(F8>60000,F8<=150000),(INT(F8/1000)*1000-60000)*10%,IF(AND(F8>150000,F8<=250000),(INT(F8/1000)*1000-150000)*15%+9000,IF(AND(F8>250000,F8<=500000),(INT(F8/1000)*1000-250000)*19%+24000,IF(F8>500000,(INT(F8/1000)*1000-500000)*30%+71500))))) -> #N/A | I8: =+'Brute allocat°'!P11 -> #N/A | J8: =+((H7+I8)/F8)*G8 -> #N/A | K8: =+'Brute allocat°'!P11*3.6% -> #N/A | L8: =+IF(AND('Brute allocat°'!D11=Base!$C$3,'Brute allocat°'!B11=Base!$A$3),('Brute allocat°'!E11/(173.333333333333))*(NETWORKDAYS('Brute allocat°'!G11,'Brute allocat°'!F11)*8),IF(AND('Brute allocat°'!D11=Base!$C$3,'Brute allocat°'!B11=Base!$A$4,'Brute allocat°'!C11=Base!$B$5),'Brute allocat°'!E11,IF(AND('Brute allocat°'!D11=Base!$C$3,'Brute allocat°'!B11=Base!$A$4,'Brute allocat°'!C11=Base!$B$4),'Brute allocat°'!E11*3,IF(AND('Brute allocat°'!D11=Base!$C$5,'Brute allocat°'!B11=Base!$A$3),('Brute allocat°'!E11/(173.333333333333))*NETWORKDAYS('Brute allocat°'!G11,'Brute allocat°'!F11)*(-8),IF(AND('Brute allocat°'!D11=Base!$C$5,'Brute allocat°'!B11=Base!$A$4,'Brute allocat°'!C11=Base!$B$5),'Brute allocat°'!E11*(-1),IF(AND('Brute allocat°'!D11=Base!$C$5,'Brute allocat°'!C11=Base!$B$4),'Brute allocat°'!E11*(-3),0)))))) -> 0 | N8: =+'Brute allocat°'!P11-'Nette allocat°'!J8-'Nette allocat°'!K8+L8+M8 -> #N/A | O8: =+'Brute allocat°'!P11*17.4% -> #N/A | P8: =+'Brute allocat°'!P11*4% -> #N/A | Q8: =+'Brute allocat°'!P11+'Nette allocat°'!O8+'Nette allocat°'!P8 -> #N/A
A9: =+'Brute allocat°'!A12 -> 0 | B9: =+VLOOKUP(A9,'Salaire moyen'!$B$5:$O$43,14,FALSE) -> #N/A | E9: =+B9+C9+D9 -> #N/A | F9: =+E9/VLOOKUP(A9,'Salaire moyen'!$B$5:$Q$43,16,FALSE) -> #N/A | G9: =+IF(F9<=60000,0,IF(AND(F9>60000,F9<=150000),(INT(F9/1000)*1000-60000)*10%,IF(AND(F9>150000,F9<=250000),(INT(F9/1000)*1000-150000)*15%+9000,IF(AND(F9>250000,F9<=500000),(INT(F9/1000)*1000-250000)*19%+24000,IF(F9>500000,(INT(F9/1000)*1000-500000)*30%+71500))))) -> #N/A | I9: =+'Brute allocat°'!P12 -> #N/A | J9: =+((H8+I9)/F9)*G9 -> #N/A | K9: =+'Brute allocat°'!P12*3.6% -> #N/A | L9: =+IF(AND('Brute allocat°'!D12=Base!$C$3,'Brute allocat°'!B12=Base!$A$3),('Brute allocat°'!E12/(173.333333333333))*(NETWORKDAYS('Brute allocat°'!G12,'Brute allocat°'!F12)*8),IF(AND('Brute allocat°'!D12=Base!$C$3,'Brute allocat°'!B12=Base!$A$4,'Brute allocat°'!C12=Base!$B$5),'Brute allocat°'!E12,IF(AND('Brute allocat°'!D12=Base!$C$3,'Brute allocat°'!B12=Base!$A$4,'Brute allocat°'!C12=Base!$B$4),'Brute allocat°'!E12*3,IF(AND('Brute allocat°'!D12=Base!$C$5,'Brute allocat°'!B12=Base!$A$3),('Brute allocat°'!E12/(173.333333333333))*NETWORKDAYS('Brute allocat°'!G12,'Brute allocat°'!F12)*(-8),IF(AND('Brute allocat°'!D12=Base!$C$5,'Brute allocat°'!B12=Base!$A$4,'Brute allocat°'!C12=Base!$B$5),'Brute allocat°'!E12*(-1),IF(AND('Brute allocat°'!D12=Base!$C$5,'Brute allocat°'!C12=Base!$B$4),'Brute allocat°'!E12*(-3),0)))))) -> 0 | N9: =+'Brute allocat°'!P12-'Nette allocat°'!J9-'Nette allocat°'!K9+L9+M9 -> #N/A | O9: =+'Brute allocat°'!P12*17.4% -> #N/A | P9: =+'Brute allocat°'!P12*4% -> #N/A | Q9: =+'Brute allocat°'!P12+'Nette allocat°'!O9+'Nette allocat°'!P9 -> #N/A
A10: =+'Brute allocat°'!A13 -> 0 | B10: =+VLOOKUP(A10,'Salaire moyen'!$B$5:$O$43,14,FALSE) -> #N/A | E10: =+B10+C10+D10 -> #N/A | F10: =+E10/VLOOKUP(A10,'Salaire moyen'!$B$5:$Q$43,16,FALSE) -> #N/A | G10: =+IF(F10<=60000,0,IF(AND(F10>60000,F10<=150000),(INT(F10/1000)*1000-60000)*10%,IF(AND(F10>150000,F10<=250000),(INT(F10/1000)*1000-150000)*15%+9000,IF(AND(F10>250000,F10<=500000),(INT(F10/1000)*1000-250000)*19%+24000,IF(F10>500000,(INT(F10/1000)*1000-500000)*30%+71500))))) -> #N/A | I10: =+'Brute allocat°'!P13 -> #N/A | J10: =+((H9+I10)/F10)*G10 -> #N/A | K10: =+'Brute allocat°'!P13*3.6% -> #N/A | L10: =+IF(AND('Brute allocat°'!D13=Base!$C$3,'Brute allocat°'!B13=Base!$A$3),('Brute allocat°'!E13/(173.333333333333))*(NETWORKDAYS('Brute allocat°'!G13,'Brute allocat°'!F13)*8),IF(AND('Brute allocat°'!D13=Base!$C$3,'Brute allocat°'!B13=Base!$A$4,'Brute allocat°'!C13=Base!$B$5),'Brute allocat°'!E13,IF(AND('Brute allocat°'!D13=Base!$C$3,'Brute allocat°'!B13=Base!$A$4,'Brute allocat°'!C13=Base!$B$4),'Brute allocat°'!E13*3,IF(AND('Brute allocat°'!D13=Base!$C$5,'Brute allocat°'!B13=Base!$A$3),('Brute allocat°'!E13/(173.333333333333))*NETWORKDAYS('Brute allocat°'!G13,'Brute allocat°'!F13)*(-8),IF(AND('Brute allocat°'!D13=Base!$C$5,'Brute allocat°'!B13=Base!$A$4,'Brute allocat°'!C13=Base!$B$5),'Brute allocat°'!E13*(-1),IF(AND('Brute allocat°'!D13=Base!$C$5,'Brute allocat°'!C13=Base!$B$4),'Brute allocat°'!E13*(-3),0)))))) -> 0 | N10: =+'Brute allocat°'!P13-'Nette allocat°'!J10-'Nette allocat°'!K10+L10+M10 -> #N/A | O10: =+'Brute allocat°'!P13*17.4% -> #N/A | P10: =+'Brute allocat°'!P13*4% -> #N/A | Q10: =+'Brute allocat°'!P13+'Nette allocat°'!O10+'Nette allocat°'!P10 -> #N/A
A11: =+'Brute allocat°'!A14 -> 0 | B11: =+VLOOKUP(A11,'Salaire moyen'!$B$5:$O$43,14,FALSE) -> #N/A | E11: =+B11+C11+D11 -> #N/A | F11: =+E11/VLOOKUP(A11,'Salaire moyen'!$B$5:$Q$43,16,FALSE) -> #N/A | G11: =+IF(F11<=60000,0,IF(AND(F11>60000,F11<=150000),(INT(F11/1000)*1000-60000)*10%,IF(AND(F11>150000,F11<=250000),(INT(F11/1000)*1000-150000)*15%+9000,IF(AND(F11>250000,F11<=500000),(INT(F11/1000)*1000-250000)*19%+24000,IF(F11>500000,(INT(F11/1000)*1000-500000)*30%+71500))))) -> #N/A | I11: =+'Brute allocat°'!P14 -> #N/A | J11: =+((H10+I11)/F11)*G11 -> #N/A | K11: =+'Brute allocat°'!P14*3.6% -> #N/A | L11: =+IF(AND('Brute allocat°'!D14=Base!$C$3,'Brute allocat°'!B14=Base!$A$3),('Brute allocat°'!E14/(173.333333333333))*(NETWORKDAYS('Brute allocat°'!G14,'Brute allocat°'!F14)*8),IF(AND('Brute allocat°'!D14=Base!$C$3,'Brute allocat°'!B14=Base!$A$4,'Brute allocat°'!C14=Base!$B$5),'Brute allocat°'!E14,IF(AND('Brute allocat°'!D14=Base!$C$3,'Brute allocat°'!B14=Base!$A$4,'Brute allocat°'!C14=Base!$B$4),'Brute allocat°'!E14*3,IF(AND('Brute allocat°'!D14=Base!$C$5,'Brute allocat°'!B14=Base!$A$3),('Brute allocat°'!E14/(173.333333333333))*NETWORKDAYS('Brute allocat°'!G14,'Brute allocat°'!F14)*(-8),IF(AND('Brute allocat°'!D14=Base!$C$5,'Brute allocat°'!B14=Base!$A$4,'Brute allocat°'!C14=Base!$B$5),'Brute allocat°'!E14*(-1),IF(AND('Brute allocat°'!D14=Base!$C$5,'Brute allocat°'!C14=Base!$B$4),'Brute allocat°'!E14*(-3),0)))))) -> 0 | N11: =+'Brute allocat°'!P14-'Nette allocat°'!J11-'Nette allocat°'!K11+L11+M11 -> #N/A | O11: =+'Brute allocat°'!P14*17.4% -> #N/A | P11: =+'Brute allocat°'!P14*4% -> #N/A | Q11: =+'Brute allocat°'!P14+'Nette allocat°'!O11+'Nette allocat°'!P11 -> #N/A
A12: =+'Brute allocat°'!A15 -> 0 | B12: =+VLOOKUP(A12,'Salaire moyen'!$B$5:$O$43,14,FALSE) -> #N/A | E12: =+B12+C12+D12 -> #N/A | F12: =+E12/VLOOKUP(A12,'Salaire moyen'!$B$5:$Q$43,16,FALSE) -> #N/A | G12: =+IF(F12<=60000,0,IF(AND(F12>60000,F12<=150000),(INT(F12/1000)*1000-60000)*10%,IF(AND(F12>150000,F12<=250000),(INT(F12/1000)*1000-150000)*15%+9000,IF(AND(F12>250000,F12<=500000),(INT(F12/1000)*1000-250000)*19%+24000,IF(F12>500000,(INT(F12/1000)*1000-500000)*30%+71500))))) -> #N/A | I12: =+'Brute allocat°'!P15 -> #N/A | J12: =+((H11+I12)/F12)*G12 -> #N/A | K12: =+'Brute allocat°'!P15*3.6% -> #N/A | L12: =+IF(AND('Brute allocat°'!D15=Base!$C$3,'Brute allocat°'!B15=Base!$A$3),('Brute allocat°'!E15/(173.333333333333))*(NETWORKDAYS('Brute allocat°'!G15,'Brute allocat°'!F15)*8),IF(AND('Brute allocat°'!D15=Base!$C$3,'Brute allocat°'!B15=Base!$A$4,'Brute allocat°'!C15=Base!$B$5),'Brute allocat°'!E15,IF(AND('Brute allocat°'!D15=Base!$C$3,'Brute allocat°'!B15=Base!$A$4,'Brute allocat°'!C15=Base!$B$4),'Brute allocat°'!E15*3,IF(AND('Brute allocat°'!D15=Base!$C$5,'Brute allocat°'!B15=Base!$A$3),('Brute allocat°'!E15/(173.333333333333))*NETWORKDAYS('Brute allocat°'!G15,'Brute allocat°'!F15)*(-8),IF(AND('Brute allocat°'!D15=Base!$C$5,'Brute allocat°'!B15=Base!$A$4,'Brute allocat°'!C15=Base!$B$5),'Brute allocat°'!E15*(-1),IF(AND('Brute allocat°'!D15=Base!$C$5,'Brute allocat°'!C15=Base!$B$4),'Brute allocat°'!E15*(-3),0)))))) -> 0 | N12: =+'Brute allocat°'!P15-'Nette allocat°'!J12-'Nette allocat°'!K12+L12+M12 -> #N/A | O12: =+'Brute allocat°'!P15*17.4% -> #N/A | P12: =+'Brute allocat°'!P15*4% -> #N/A | Q12: =+'Brute allocat°'!P15+'Nette allocat°'!O12+'Nette allocat°'!P12 -> #N/A
A13: =+'Brute allocat°'!A16 -> 0 | B13: =+VLOOKUP(A13,'Salaire moyen'!$B$5:$O$43,14,FALSE) -> #N/A | E13: =+B13+C13+D13 -> #N/A | F13: =+E13/VLOOKUP(A13,'Salaire moyen'!$B$5:$Q$43,16,FALSE) -> #N/A | G13: =+IF(F13<=60000,0,IF(AND(F13>60000,F13<=150000),(INT(F13/1000)*1000-60000)*10%,IF(AND(F13>150000,F13<=250000),(INT(F13/1000)*1000-150000)*15%+9000,IF(AND(F13>250000,F13<=500000),(INT(F13/1000)*1000-250000)*19%+24000,IF(F13>500000,(INT(F13/1000)*1000-500000)*30%+71500))))) -> #N/A | I13: =+'Brute allocat°'!P16 -> #N/A | J13: =+((H12+I13)/F13)*G13 -> #N/A | K13: =+'Brute allocat°'!P16*3.6% -> #N/A | L13: =+IF(AND('Brute allocat°'!D16=Base!$C$3,'Brute allocat°'!B16=Base!$A$3),('Brute allocat°'!E16/(173.333333333333))*(NETWORKDAYS('Brute allocat°'!G16,'Brute allocat°'!F16)*8),IF(AND('Brute allocat°'!D16=Base!$C$3,'Brute allocat°'!B16=Base!$A$4,'Brute allocat°'!C16=Base!$B$5),'Brute allocat°'!E16,IF(AND('Brute allocat°'!D16=Base!$C$3,'Brute allocat°'!B16=Base!$A$4,'Brute allocat°'!C16=Base!$B$4),'Brute allocat°'!E16*3,IF(AND('Brute allocat°'!D16=Base!$C$5,'Brute allocat°'!B16=Base!$A$3),('Brute allocat°'!E16/(173.333333333333))*NETWORKDAYS('Brute allocat°'!G16,'Brute allocat°'!F16)*(-8),IF(AND('Brute allocat°'!D16=Base!$C$5,'Brute allocat°'!B16=Base!$A$4,'Brute allocat°'!C16=Base!$B$5),'Brute allocat°'!E16*(-1),IF(AND('Brute allocat°'!D16=Base!$C$5,'Brute allocat°'!C16=Base!$B$4),'Brute allocat°'!E16*(-3),0)))))) -> 0 | N13: =+'Brute allocat°'!P16-'Nette allocat°'!J13-'Nette allocat°'!K13+L13+M13 -> #N/A | O13: =+'Brute allocat°'!P16*17.4% -> #N/A | P13: =+'Brute allocat°'!P16*4% -> #N/A | Q13: =+'Brute allocat°'!P16+'Nette allocat°'!O13+'Nette allocat°'!P13 -> #N/A
A14: =+'Brute allocat°'!A17 -> 0 | B14: =+VLOOKUP(A14,'Salaire moyen'!$B$5:$O$43,14,FALSE) -> #N/A | E14: =+B14+C14+D14 -> #N/A | F14: =+E14/VLOOKUP(A14,'Salaire moyen'!$B$5:$Q$43,16,FALSE) -> #N/A | G14: =+IF(F14<=60000,0,IF(AND(F14>60000,F14<=150000),(INT(F14/1000)*1000-60000)*10%,IF(AND(F14>150000,F14<=250000),(INT(F14/1000)*1000-150000)*15%+9000,IF(AND(F14>250000,F14<=500000),(INT(F14/1000)*1000-250000)*19%+24000,IF(F14>500000,(INT(F14/1000)*1000-500000)*30%+71500))))) -> #N/A | I14: =+'Brute allocat°'!P17 -> #N/A | J14: =+((H13+I14)/F14)*G14 -> #N/A | K14: =+'Brute allocat°'!P17*3.6% -> #N/A | L14: =+IF(AND('Brute allocat°'!D17=Base!$C$3,'Brute allocat°'!B17=Base!$A$3),('Brute allocat°'!E17/(173.333333333333))*(NETWORKDAYS('Brute allocat°'!G17,'Brute allocat°'!F17)*8),IF(AND('Brute allocat°'!D17=Base!$C$3,'Brute allocat°'!B17=Base!$A$4,'Brute allocat°'!C17=Base!$B$5),'Brute allocat°'!E17,IF(AND('Brute allocat°'!D17=Base!$C$3,'Brute allocat°'!B17=Base!$A$4,'Brute allocat°'!C17=Base!$B$4),'Brute allocat°'!E17*3,IF(AND('Brute allocat°'!D17=Base!$C$5,'Brute allocat°'!B17=Base!$A$3),('Brute allocat°'!E17/(173.333333333333))*NETWORKDAYS('Brute allocat°'!G17,'Brute allocat°'!F17)*(-8),IF(AND('Brute allocat°'!D17=Base!$C$5,'Brute allocat°'!B17=Base!$A$4,'Brute allocat°'!C17=Base!$B$5),'Brute allocat°'!E17*(-1),IF(AND('Brute allocat°'!D17=Base!$C$5,'Brute allocat°'!C17=Base!$B$4),'Brute allocat°'!E17*(-3),0)))))) -> 0 | N14: =+'Brute allocat°'!P17-'Nette allocat°'!J14-'Nette allocat°'!K14+L14+M14 -> #N/A | O14: =+'Brute allocat°'!P17*17.4% -> #N/A | P14: =+'Brute allocat°'!P17*4% -> #N/A | Q14: =+'Brute allocat°'!P17+'Nette allocat°'!O14+'Nette allocat°'!P14 -> #N/A
A15: =+'Brute allocat°'!A18 -> 0 | B15: =+VLOOKUP(A15,'Salaire moyen'!$B$5:$O$43,14,FALSE) -> #N/A | E15: =+B15+C15+D15 -> #N/A | F15: =+E15/VLOOKUP(A15,'Salaire moyen'!$B$5:$Q$43,16,FALSE) -> #N/A | G15: =+IF(F15<=60000,0,IF(AND(F15>60000,F15<=150000),(INT(F15/1000)*1000-60000)*10%,IF(AND(F15>150000,F15<=250000),(INT(F15/1000)*1000-150000)*15%+9000,IF(AND(F15>250000,F15<=500000),(INT(F15/1000)*1000-250000)*19%+24000,IF(F15>500000,(INT(F15/1000)*1000-500000)*30%+71500))))) -> #N/A | I15: =+'Brute allocat°'!P18 -> #N/A | J15: =+((H14+I15)/F15)*G15 -> #N/A | K15: =+'Brute allocat°'!P18*3.6% -> #N/A | L15: =+IF(AND('Brute allocat°'!D18=Base!$C$3,'Brute allocat°'!B18=Base!$A$3),('Brute allocat°'!E18/(173.333333333333))*(NETWORKDAYS('Brute allocat°'!G18,'Brute allocat°'!F18)*8),IF(AND('Brute allocat°'!D18=Base!$C$3,'Brute allocat°'!B18=Base!$A$4,'Brute allocat°'!C18=Base!$B$5),'Brute allocat°'!E18,IF(AND('Brute allocat°'!D18=Base!$C$3,'Brute allocat°'!B18=Base!$A$4,'Brute allocat°'!C18=Base!$B$4),'Brute allocat°'!E18*3,IF(AND('Brute allocat°'!D18=Base!$C$5,'Brute allocat°'!B18=Base!$A$3),('Brute allocat°'!E18/(173.333333333333))*NETWORKDAYS('Brute allocat°'!G18,'Brute allocat°'!F18)*(-8),IF(AND('Brute allocat°'!D18=Base!$C$5,'Brute allocat°'!B18=Base!$A$4,'Brute allocat°'!C18=Base!$B$5),'Brute allocat°'!E18*(-1),IF(AND('Brute allocat°'!D18=Base!$C$5,'Brute allocat°'!C18=Base!$B$4),'Brute allocat°'!E18*(-3),0)))))) -> 0 | N15: =+'Brute allocat°'!P18-'Nette allocat°'!J15-'Nette allocat°'!K15+L15+M15 -> #N/A | O15: =+'Brute allocat°'!P18*17.4% -> #N/A | P15: =+'Brute allocat°'!P18*4% -> #N/A | Q15: =+'Brute allocat°'!P18+'Nette allocat°'!O15+'Nette allocat°'!P15 -> #N/A
A16: =+'Brute allocat°'!A19 -> 0 | B16: =+VLOOKUP(A16,'Salaire moyen'!$B$5:$O$43,14,FALSE) -> #N/A | E16: =+B16+C16+D16 -> #N/A | F16: =+E16/VLOOKUP(A16,'Salaire moyen'!$B$5:$Q$43,16,FALSE) -> #N/A | G16: =+IF(F16<=60000,0,IF(AND(F16>60000,F16<=150000),(INT(F16/1000)*1000-60000)*10%,IF(AND(F16>150000,F16<=250000),(INT(F16/1000)*1000-150000)*15%+9000,IF(AND(F16>250000,F16<=500000),(INT(F16/1000)*1000-250000)*19%+24000,IF(F16>500000,(INT(F16/1000)*1000-500000)*30%+71500))))) -> #N/A | I16: =+'Brute allocat°'!P19 -> #N/A | J16: =+((H15+I16)/F16)*G16 -> #N/A | K16: =+'Brute allocat°'!P19*3.6% -> #N/A | L16: =+IF(AND('Brute allocat°'!D19=Base!$C$3,'Brute allocat°'!B19=Base!$A$3),('Brute allocat°'!E19/(173.333333333333))*(NETWORKDAYS('Brute allocat°'!G19,'Brute allocat°'!F19)*8),IF(AND('Brute allocat°'!D19=Base!$C$3,'Brute allocat°'!B19=Base!$A$4,'Brute allocat°'!C19=Base!$B$5),'Brute allocat°'!E19,IF(AND('Brute allocat°'!D19=Base!$C$3,'Brute allocat°'!B19=Base!$A$4,'Brute allocat°'!C19=Base!$B$4),'Brute allocat°'!E19*3,IF(AND('Brute allocat°'!D19=Base!$C$5,'Brute allocat°'!B19=Base!$A$3),('Brute allocat°'!E19/(173.333333333333))*NETWORKDAYS('Brute allocat°'!G19,'Brute allocat°'!F19)*(-8),IF(AND('Brute allocat°'!D19=Base!$C$5,'Brute allocat°'!B19=Base!$A$4,'Brute allocat°'!C19=Base!$B$5),'Brute allocat°'!E19*(-1),IF(AND('Brute allocat°'!D19=Base!$C$5,'Brute allocat°'!C19=Base!$B$4),'Brute allocat°'!E19*(-3),0)))))) -> 0 | N16: =+'Brute allocat°'!P19-'Nette allocat°'!J16-'Nette allocat°'!K16+L16+M16 -> #N/A | O16: =+'Brute allocat°'!P19*17.4% -> #N/A | P16: =+'Brute allocat°'!P19*4% -> #N/A | Q16: =+'Brute allocat°'!P19+'Nette allocat°'!O16+'Nette allocat°'!P16 -> #N/A
A17: =+'Brute allocat°'!A20 -> 0 | B17: =+VLOOKUP(A17,'Salaire moyen'!$B$5:$O$43,14,FALSE) -> #N/A | E17: =+B17+C17+D17 -> #N/A | F17: =+E17/VLOOKUP(A17,'Salaire moyen'!$B$5:$Q$43,16,FALSE) -> #N/A | G17: =+IF(F17<=60000,0,IF(AND(F17>60000,F17<=150000),(INT(F17/1000)*1000-60000)*10%,IF(AND(F17>150000,F17<=250000),(INT(F17/1000)*1000-150000)*15%+9000,IF(AND(F17>250000,F17<=500000),(INT(F17/1000)*1000-250000)*19%+24000,IF(F17>500000,(INT(F17/1000)*1000-500000)*30%+71500))))) -> #N/A | I17: =+'Brute allocat°'!P20 -> #N/A | J17: =+((H16+I17)/F17)*G17 -> #N/A | K17: =+'Brute allocat°'!P20*3.6% -> #N/A | L17: =+IF(AND('Brute allocat°'!D20=Base!$C$3,'Brute allocat°'!B20=Base!$A$3),('Brute allocat°'!E20/(173.333333333333))*(NETWORKDAYS('Brute allocat°'!G20,'Brute allocat°'!F20)*8),IF(AND('Brute allocat°'!D20=Base!$C$3,'Brute allocat°'!B20=Base!$A$4,'Brute allocat°'!C20=Base!$B$5),'Brute allocat°'!E20,IF(AND('Brute allocat°'!D20=Base!$C$3,'Brute allocat°'!B20=Base!$A$4,'Brute allocat°'!C20=Base!$B$4),'Brute allocat°'!E20*3,IF(AND('Brute allocat°'!D20=Base!$C$5,'Brute allocat°'!B20=Base!$A$3),('Brute allocat°'!E20/(173.333333333333))*NETWORKDAYS('Brute allocat°'!G20,'Brute allocat°'!F20)*(-8),IF(AND('Brute allocat°'!D20=Base!$C$5,'Brute allocat°'!B20=Base!$A$4,'Brute allocat°'!C20=Base!$B$5),'Brute allocat°'!E20*(-1),IF(AND('Brute allocat°'!D20=Base!$C$5,'Brute allocat°'!C20=Base!$B$4),'Brute allocat°'!E20*(-3),0)))))) -> 0 | N17: =+'Brute allocat°'!P20-'Nette allocat°'!J17-'Nette allocat°'!K17+L17+M17 -> #N/A | O17: =+'Brute allocat°'!P20*17.4% -> #N/A | P17: =+'Brute allocat°'!P20*4% -> #N/A | Q17: =+'Brute allocat°'!P20+'Nette allocat°'!O17+'Nette allocat°'!P17 -> #N/A
... A29: =+'Brute allocat°'!A32 -> 0 | B29: =+VLOOKUP(A29,'Salaire moyen'!$B$5:$O$43,14,FALSE) -> #N/A | E29: =+B29+C29+D29 -> #N/A | F29: =+E29/VLOOKUP(A29,'Salaire moyen'!$B$5:$Q$43,16,FALSE) -> #N/A | G29: =+IF(F29<=60000,0,IF(AND(F29>60000,F29<=150000),(INT(F29/1000)*1000-60000)*10%,IF(AND(F29>150000,F29<=250000),(INT(F29/1000)*1000-150000)*15%+9000,IF(AND(F29>250000,F29<=500000),(INT(F29/1000)*1000-250000)*19%+24000,IF(F29>500000,(INT(F29/1000)*1000-500000)*30%+71500))))) -> #N/A | I29: =+'Brute allocat°'!P32 -> #N/A | J29: =+((H28+I29)/F29)*G29 -> #N/A | K29: =+'Brute allocat°'!P32*3.6% -> #N/A | L29: =+IF(AND('Brute allocat°'!D32=Base!$C$3,'Brute allocat°'!B32=Base!$A$3),('Brute allocat°'!E32/(173.333333333333))*(NETWORKDAYS('Brute allocat°'!G32,'Brute allocat°'!F32)*8),IF(AND('Brute allocat°'!D32=Base!$C$3,'Brute allocat°'!B32=Base!$A$4,'Brute allocat°'!C32=Base!$B$5),'Brute allocat°'!E32,IF(AND('Brute allocat°'!D32=Base!$C$3,'Brute allocat°'!B32=Base!$A$4,'Brute allocat°'!C32=Base!$B$4),'Brute allocat°'!E32*3,IF(AND('Brute allocat°'!D32=Base!$C$5,'Brute allocat°'!B32=Base!$A$3),('Brute allocat°'!E32/(173.333333333333))*NETWORKDAYS('Brute allocat°'!G32,'Brute allocat°'!F32)*(-8),IF(AND('Brute allocat°'!D32=Base!$C$5,'Brute allocat°'!B32=Base!$A$4,'Brute allocat°'!C32=Base!$B$5),'Brute allocat°'!E32*(-1),IF(AND('Brute allocat°'!D32=Base!$C$5,'Brute allocat°'!C32=Base!$B$4),'Brute allocat°'!E32*(-3),0)))))) -> 0 | N29: =+'Brute allocat°'!P32-'Nette allocat°'!J29-'Nette allocat°'!K29+L29+M29 -> #N/A | O29: =+'Brute allocat°'!P32*17.4% -> #N/A | P29: =+'Brute allocat°'!P32*4% -> #N/A | Q29: =+'Brute allocat°'!P32+'Nette allocat°'!O29+'Nette allocat°'!P29 -> #N/A
A30: =+'Brute allocat°'!#REF! -> #REF! | B30: =+VLOOKUP(A30,'Salaire moyen'!$B$5:$O$43,14,FALSE) -> #REF! | E30: =+B30+C30+D30 -> #REF! | F30: =+E30/VLOOKUP(A30,'Salaire moyen'!$B$5:$Q$43,16,FALSE) -> #REF! | G30: =+IF(F30<=60000,0,IF(AND(F30>60000,F30<=150000),(INT(F30/1000)*1000-60000)*10%,IF(AND(F30>150000,F30<=250000),(INT(F30/1000)*1000-150000)*15%+9000,IF(AND(F30>250000,F30<=500000),(INT(F30/1000)*1000-250000)*19%+24000,IF(F30>500000,(INT(F30/1000)*1000-500000)*30%+71500))))) -> #REF! | I30: =+'Brute allocat°'!#REF! -> #REF! | J30: =+((H29+I30)/F30)*G30 -> #REF! | K30: =+'Brute allocat°'!#REF!*3.6% -> #REF! | L30: =+IF(AND('Brute allocat°'!#REF!=Base!$C$3,'Brute allocat°'!#REF!=Base!$A$3),('Brute allocat°'!#REF!/(173.333333333333))*(NETWORKDAYS('Brute allocat°'!#REF!,'Brute allocat°'!#REF!)*8),IF(AND('Brute allocat°'!#REF!=Base!$C$3,'Brute allocat°'!#REF!=Base!$A$4,'Brute allocat°'!#REF!=Base!$B$5),'Brute allocat°'!#REF!,IF(AND('Brute allocat°'!#REF!=Base!$C$3,'Brute allocat°'!#REF!=Base!$A$4,'Brute allocat°'!#REF!=Base!$B$4),'Brute allocat°'!#REF!*3,IF(AND('Brute allocat°'!#REF!=Base!$C$5,'Brute allocat°'!#REF!=Base!$A$3),('Brute allocat°'!#REF!/(173.333333333333))*NETWORKDAYS('Brute allocat°'!#REF!,'Brute allocat°'!#REF!)*(-8),IF(AND('Brute allocat°'!#REF!=Base!$C$5,'Brute allocat°'!#REF!=Base!$A$4,'Brute allocat°'!#REF!=Base!$B$5),'Brute allocat°'!#REF!*(-1),IF(AND('Brute allocat°'!#REF!=Base!$C$5,'Brute allocat°'!#REF!=Base!$B$4),'Brute allocat°'!#REF!*(-3),0)))))) -> #REF! | N30: =+'Brute allocat°'!#REF!-'Nette allocat°'!J30-'Nette allocat°'!K30+L30+M30 -> #REF! | O30: =+'Brute allocat°'!#REF!*17.4% -> #REF! | P30: =+'Brute allocat°'!#REF!*4% -> #REF! | Q30: =+'Brute allocat°'!#REF!+'Nette allocat°'!O30+'Nette allocat°'!P30 -> #REF!
A31: =+'Brute allocat°'!A33 -> 0 | B31: =+VLOOKUP(A31,'Salaire moyen'!$B$5:$O$43,14,FALSE) -> #N/A | E31: =+B31+C31+D31 -> #N/A | F31: =+E31/VLOOKUP(A31,'Salaire moyen'!$B$5:$Q$43,16,FALSE) -> #N/A | G31: =+IF(F31<=60000,0,IF(AND(F31>60000,F31<=150000),(INT(F31/1000)*1000-60000)*10%,IF(AND(F31>150000,F31<=250000),(INT(F31/1000)*1000-150000)*15%+9000,IF(AND(F31>250000,F31<=500000),(INT(F31/1000)*1000-250000)*19%+24000,IF(F31>500000,(INT(F31/1000)*1000-500000)*30%+71500))))) -> #N/A | I31: =+'Brute allocat°'!P33 -> #N/A | J31: =+((H30+I31)/F31)*G31 -> #N/A | K31: =+'Brute allocat°'!P33*3.6% -> #N/A | L31: =+IF(AND('Brute allocat°'!D33=Base!$C$3,'Brute allocat°'!B33=Base!$A$3),('Brute allocat°'!E33/(173.333333333333))*(NETWORKDAYS('Brute allocat°'!G33,'Brute allocat°'!F33)*8),IF(AND('Brute allocat°'!D33=Base!$C$3,'Brute allocat°'!B33=Base!$A$4,'Brute allocat°'!C33=Base!$B$5),'Brute allocat°'!E33,IF(AND('Brute allocat°'!D33=Base!$C$3,'Brute allocat°'!B33=Base!$A$4,'Brute allocat°'!C33=Base!$B$4),'Brute allocat°'!E33*3,IF(AND('Brute allocat°'!D33=Base!$C$5,'Brute allocat°'!B33=Base!$A$3),('Brute allocat°'!E33/(173.333333333333))*NETWORKDAYS('Brute allocat°'!G33,'Brute allocat°'!F33)*(-8),IF(AND('Brute allocat°'!D33=Base!$C$5,'Brute allocat°'!B33=Base!$A$4,'Brute allocat°'!C33=Base!$B$5),'Brute allocat°'!E33*(-1),IF(AND('Brute allocat°'!D33=Base!$C$5,'Brute allocat°'!C33=Base!$B$4),'Brute allocat°'!E33*(-3),0)))))) -> 0 | N31: =+'Brute allocat°'!P33-'Nette allocat°'!J31-'Nette allocat°'!K31+L31+M31 -> #N/A | O31: =+'Brute allocat°'!P33*17.4% -> #N/A | P31: =+'Brute allocat°'!P33*4% -> #N/A | Q31: =+'Brute allocat°'!P33+'Nette allocat°'!O31+'Nette allocat°'!P31 -> #N/A
A32: =+'Brute allocat°'!A34 -> 0 | B32: =+VLOOKUP(A32,'Salaire moyen'!$B$5:$O$43,14,FALSE) -> #N/A | E32: =+B32+C32+D32 -> #N/A | F32: =+E32/VLOOKUP(A32,'Salaire moyen'!$B$5:$Q$43,16,FALSE) -> #N/A | G32: =+IF(F32<=60000,0,IF(AND(F32>60000,F32<=150000),(INT(F32/1000)*1000-60000)*10%,IF(AND(F32>150000,F32<=250000),(INT(F32/1000)*1000-150000)*15%+9000,IF(AND(F32>250000,F32<=500000),(INT(F32/1000)*1000-250000)*19%+24000,IF(F32>500000,(INT(F32/1000)*1000-500000)*30%+71500))))) -> #N/A | I32: =+'Brute allocat°'!P34 -> #N/A | J32: =+((H31+I32)/F32)*G32 -> #N/A | K32: =+'Brute allocat°'!P34*3.6% -> #N/A | L32: =+IF(AND('Brute allocat°'!D34=Base!$C$3,'Brute allocat°'!B34=Base!$A$3),('Brute allocat°'!E34/(173.333333333333))*(NETWORKDAYS('Brute allocat°'!G34,'Brute allocat°'!F34)*8),IF(AND('Brute allocat°'!D34=Base!$C$3,'Brute allocat°'!B34=Base!$A$4,'Brute allocat°'!C34=Base!$B$5),'Brute allocat°'!E34,IF(AND('Brute allocat°'!D34=Base!$C$3,'Brute allocat°'!B34=Base!$A$4,'Brute allocat°'!C34=Base!$B$4),'Brute allocat°'!E34*3,IF(AND('Brute allocat°'!D34=Base!$C$5,'Brute allocat°'!B34=Base!$A$3),('Brute allocat°'!E34/(173.333333333333))*NETWORKDAYS('Brute allocat°'!G34,'Brute allocat°'!F34)*(-8),IF(AND('Brute allocat°'!D34=Base!$C$5,'Brute allocat°'!B34=Base!$A$4,'Brute allocat°'!C34=Base!$B$5),'Brute allocat°'!E34*(-1),IF(AND('Brute allocat°'!D34=Base!$C$5,'Brute allocat°'!C34=Base!$B$4),'Brute allocat°'!E34*(-3),0)))))) -> 0 | N32: =+'Brute allocat°'!P34-'Nette allocat°'!J32-'Nette allocat°'!K32+L32+M32 -> #N/A | O32: =+'Brute allocat°'!P34*17.4% -> #N/A | P32: =+'Brute allocat°'!P34*4% -> #N/A | Q32: =+'Brute allocat°'!P34+'Nette allocat°'!O32+'Nette allocat°'!P32 -> #N/A
A33: =+'Brute allocat°'!A35 -> 0 | B33: =+VLOOKUP(A33,'Salaire moyen'!$B$5:$O$43,14,FALSE) -> #N/A | E33: =+B33+C33+D33 -> #N/A | F33: =+E33/VLOOKUP(A33,'Salaire moyen'!$B$5:$Q$43,16,FALSE) -> #N/A | G33: =+IF(F33<=60000,0,IF(AND(F33>60000,F33<=150000),(INT(F33/1000)*1000-60000)*10%,IF(AND(F33>150000,F33<=250000),(INT(F33/1000)*1000-150000)*15%+9000,IF(AND(F33>250000,F33<=500000),(INT(F33/1000)*1000-250000)*19%+24000,IF(F33>500000,(INT(F33/1000)*1000-500000)*30%+71500))))) -> #N/A | I33: =+'Brute allocat°'!P35 -> #N/A | J33: =+((H32+I33)/F33)*G33 -> #N/A | K33: =+'Brute allocat°'!P35*3.6% -> #N/A | L33: =+IF(AND('Brute allocat°'!D35=Base!$C$3,'Brute allocat°'!B35=Base!$A$3),('Brute allocat°'!E35/(173.333333333333))*(NETWORKDAYS('Brute allocat°'!G35,'Brute allocat°'!F35)*8),IF(AND('Brute allocat°'!D35=Base!$C$3,'Brute allocat°'!B35=Base!$A$4,'Brute allocat°'!C35=Base!$B$5),'Brute allocat°'!E35,IF(AND('Brute allocat°'!D35=Base!$C$3,'Brute allocat°'!B35=Base!$A$4,'Brute allocat°'!C35=Base!$B$4),'Brute allocat°'!E35*3,IF(AND('Brute allocat°'!D35=Base!$C$5,'Brute allocat°'!B35=Base!$A$3),('Brute allocat°'!E35/(173.333333333333))*NETWORKDAYS('Brute allocat°'!G35,'Brute allocat°'!F35)*(-8),IF(AND('Brute allocat°'!D35=Base!$C$5,'Brute allocat°'!B35=Base!$A$4,'Brute allocat°'!C35=Base!$B$5),'Brute allocat°'!E35*(-1),IF(AND('Brute allocat°'!D35=Base!$C$5,'Brute allocat°'!C35=Base!$B$4),'Brute allocat°'!E35*(-3),0)))))) -> 0 | N33: =+'Brute allocat°'!P35-'Nette allocat°'!J33-'Nette allocat°'!K33+L33+M33 -> #N/A | O33: =+'Brute allocat°'!P35*17.4% -> #N/A | P33: =+'Brute allocat°'!P35*4% -> #N/A | Q33: =+'Brute allocat°'!P35+'Nette allocat°'!O33+'Nette allocat°'!P33 -> #N/A
A34: =+'Brute allocat°'!A36 -> 0 | B34: =+VLOOKUP(A34,'Salaire moyen'!$B$5:$O$43,14,FALSE) -> #N/A | E34: =+B34+C34+D34 -> #N/A | F34: =+E34/VLOOKUP(A34,'Salaire moyen'!$B$5:$Q$43,16,FALSE) -> #N/A | G34: =+IF(F34<=60000,0,IF(AND(F34>60000,F34<=150000),(INT(F34/1000)*1000-60000)*10%,IF(AND(F34>150000,F34<=250000),(INT(F34/1000)*1000-150000)*15%+9000,IF(AND(F34>250000,F34<=500000),(INT(F34/1000)*1000-250000)*19%+24000,IF(F34>500000,(INT(F34/1000)*1000-500000)*30%+71500))))) -> #N/A | I34: =+'Brute allocat°'!P36 -> #N/A | J34: =+((H33+I34)/F34)*G34 -> #N/A | K34: =+'Brute allocat°'!P36*3.6% -> #N/A | L34: =+IF(AND('Brute allocat°'!D36=Base!$C$3,'Brute allocat°'!B36=Base!$A$3),('Brute allocat°'!E36/(173.333333333333))*(NETWORKDAYS('Brute allocat°'!G36,'Brute allocat°'!F36)*8),IF(AND('Brute allocat°'!D36=Base!$C$3,'Brute allocat°'!B36=Base!$A$4,'Brute allocat°'!C36=Base!$B$5),'Brute allocat°'!E36,IF(AND('Brute allocat°'!D36=Base!$C$3,'Brute allocat°'!B36=Base!$A$4,'Brute allocat°'!C36=Base!$B$4),'Brute allocat°'!E36*3,IF(AND('Brute allocat°'!D36=Base!$C$5,'Brute allocat°'!B36=Base!$A$3),('Brute allocat°'!E36/(173.333333333333))*NETWORKDAYS('Brute allocat°'!G36,'Brute allocat°'!F36)*(-8),IF(AND('Brute allocat°'!D36=Base!$C$5,'Brute allocat°'!B36=Base!$A$4,'Brute allocat°'!C36=Base!$B$5),'Brute allocat°'!E36*(-1),IF(AND('Brute allocat°'!D36=Base!$C$5,'Brute allocat°'!C36=Base!$B$4),'Brute allocat°'!E36*(-3),0)))))) -> 0 | N34: =+'Brute allocat°'!P36-'Nette allocat°'!J34-'Nette allocat°'!K34+L34+M34 -> #N/A | O34: =+'Brute allocat°'!P36*17.4% -> #N/A | P34: =+'Brute allocat°'!P36*4% -> #N/A | Q34: =+'Brute allocat°'!P36+'Nette allocat°'!O34+'Nette allocat°'!P34 -> #N/A
A35: =+'Brute allocat°'!A37 -> 0 | B35: =+VLOOKUP(A35,'Salaire moyen'!$B$5:$O$43,14,FALSE) -> #N/A | E35: =+B35+C35+D35 -> #N/A | F35: =+E35/VLOOKUP(A35,'Salaire moyen'!$B$5:$Q$43,16,FALSE) -> #N/A | G35: =+IF(F35<=60000,0,IF(AND(F35>60000,F35<=150000),(INT(F35/1000)*1000-60000)*10%,IF(AND(F35>150000,F35<=250000),(INT(F35/1000)*1000-150000)*15%+9000,IF(AND(F35>250000,F35<=500000),(INT(F35/1000)*1000-250000)*19%+24000,IF(F35>500000,(INT(F35/1000)*1000-500000)*30%+71500))))) -> #N/A | I35: =+'Brute allocat°'!P37 -> #N/A | J35: =+((H34+I35)/F35)*G35 -> #N/A | K35: =+'Brute allocat°'!P37*3.6% -> #N/A | L35: =+IF(AND('Brute allocat°'!D37=Base!$C$3,'Brute allocat°'!B37=Base!$A$3),('Brute allocat°'!E37/(173.333333333333))*(NETWORKDAYS('Brute allocat°'!G37,'Brute allocat°'!F37)*8),IF(AND('Brute allocat°'!D37=Base!$C$3,'Brute allocat°'!B37=Base!$A$4,'Brute allocat°'!C37=Base!$B$5),'Brute allocat°'!E37,IF(AND('Brute allocat°'!D37=Base!$C$3,'Brute allocat°'!B37=Base!$A$4,'Brute allocat°'!C37=Base!$B$4),'Brute allocat°'!E37*3,IF(AND('Brute allocat°'!D37=Base!$C$5,'Brute allocat°'!B37=Base!$A$3),('Brute allocat°'!E37/(173.333333333333))*NETWORKDAYS('Brute allocat°'!G37,'Brute allocat°'!F37)*(-8),IF(AND('Brute allocat°'!D37=Base!$C$5,'Brute allocat°'!B37=Base!$A$4,'Brute allocat°'!C37=Base!$B$5),'Brute allocat°'!E37*(-1),IF(AND('Brute allocat°'!D37=Base!$C$5,'Brute allocat°'!C37=Base!$B$4),'Brute allocat°'!E37*(-3),0)))))) -> 0 | N35: =+'Brute allocat°'!P37-'Nette allocat°'!J35-'Nette allocat°'!K35+L35+M35 -> #N/A | O35: =+'Brute allocat°'!P37*17.4% -> #N/A | P35: =+'Brute allocat°'!P37*4% -> #N/A | Q35: =+'Brute allocat°'!P37+'Nette allocat°'!O35+'Nette allocat°'!P35 -> #N/A
A36: =+'Brute allocat°'!A38 -> 0 | B36: =+VLOOKUP(A36,'Salaire moyen'!$B$5:$O$43,14,FALSE) -> #N/A | E36: =+B36+C36+D36 -> #N/A | F36: =+E36/VLOOKUP(A36,'Salaire moyen'!$B$5:$Q$43,16,FALSE) -> #N/A | G36: =+IF(F36<=60000,0,IF(AND(F36>60000,F36<=150000),(INT(F36/1000)*1000-60000)*10%,IF(AND(F36>150000,F36<=250000),(INT(F36/1000)*1000-150000)*15%+9000,IF(AND(F36>250000,F36<=500000),(INT(F36/1000)*1000-250000)*19%+24000,IF(F36>500000,(INT(F36/1000)*1000-500000)*30%+71500))))) -> #N/A | I36: =+'Brute allocat°'!P38 -> #N/A | J36: =+((H35+I36)/F36)*G36 -> #N/A | K36: =+'Brute allocat°'!P38*3.6% -> #N/A | L36: =+IF(AND('Brute allocat°'!D38=Base!$C$3,'Brute allocat°'!B38=Base!$A$3),('Brute allocat°'!E38/(173.333333333333))*(NETWORKDAYS('Brute allocat°'!G38,'Brute allocat°'!F38)*8),IF(AND('Brute allocat°'!D38=Base!$C$3,'Brute allocat°'!B38=Base!$A$4,'Brute allocat°'!C38=Base!$B$5),'Brute allocat°'!E38,IF(AND('Brute allocat°'!D38=Base!$C$3,'Brute allocat°'!B38=Base!$A$4,'Brute allocat°'!C38=Base!$B$4),'Brute allocat°'!E38*3,IF(AND('Brute allocat°'!D38=Base!$C$5,'Brute allocat°'!B38=Base!$A$3),('Brute allocat°'!E38/(173.333333333333))*NETWORKDAYS('Brute allocat°'!G38,'Brute allocat°'!F38)*(-8),IF(AND('Brute allocat°'!D38=Base!$C$5,'Brute allocat°'!B38=Base!$A$4,'Brute allocat°'!C38=Base!$B$5),'Brute allocat°'!E38*(-1),IF(AND('Brute allocat°'!D38=Base!$C$5,'Brute allocat°'!C38=Base!$B$4),'Brute allocat°'!E38*(-3),0)))))) -> 0 | N36: =+'Brute allocat°'!P38-'Nette allocat°'!J36-'Nette allocat°'!K36+L36+M36 -> #N/A | O36: =+'Brute allocat°'!P38*17.4% -> #N/A | P36: =+'Brute allocat°'!P38*4% -> #N/A | Q36: =+'Brute allocat°'!P38+'Nette allocat°'!O36+'Nette allocat°'!P36 -> #N/A
A37: =+'Brute allocat°'!A39 -> 0 | B37: =+VLOOKUP(A37,'Salaire moyen'!$B$5:$O$43,14,FALSE) -> #N/A | E37: =+B37+C37+D37 -> #N/A | F37: =+E37/VLOOKUP(A37,'Salaire moyen'!$B$5:$Q$43,16,FALSE) -> #N/A | G37: =+IF(F37<=60000,0,IF(AND(F37>60000,F37<=150000),(INT(F37/1000)*1000-60000)*10%,IF(AND(F37>150000,F37<=250000),(INT(F37/1000)*1000-150000)*15%+9000,IF(AND(F37>250000,F37<=500000),(INT(F37/1000)*1000-250000)*19%+24000,IF(F37>500000,(INT(F37/1000)*1000-500000)*30%+71500))))) -> #N/A | I37: =+'Brute allocat°'!P39 -> #N/A | J37: =+((H36+I37)/F37)*G37 -> #N/A | K37: =+'Brute allocat°'!P39*3.6% -> #N/A | L37: =+IF(AND('Brute allocat°'!D39=Base!$C$3,'Brute allocat°'!B39=Base!$A$3),('Brute allocat°'!E39/(173.333333333333))*(NETWORKDAYS('Brute allocat°'!G39,'Brute allocat°'!F39)*8),IF(AND('Brute allocat°'!D39=Base!$C$3,'Brute allocat°'!B39=Base!$A$4,'Brute allocat°'!C39=Base!$B$5),'Brute allocat°'!E39,IF(AND('Brute allocat°'!D39=Base!$C$3,'Brute allocat°'!B39=Base!$A$4,'Brute allocat°'!C39=Base!$B$4),'Brute allocat°'!E39*3,IF(AND('Brute allocat°'!D39=Base!$C$5,'Brute allocat°'!B39=Base!$A$3),('Brute allocat°'!E39/(173.333333333333))*NETWORKDAYS('Brute allocat°'!G39,'Brute allocat°'!F39)*(-8),IF(AND('Brute allocat°'!D39=Base!$C$5,'Brute allocat°'!B39=Base!$A$4,'Brute allocat°'!C39=Base!$B$5),'Brute allocat°'!E39*(-1),IF(AND('Brute allocat°'!D39=Base!$C$5,'Brute allocat°'!C39=Base!$B$4),'Brute allocat°'!E39*(-3),0)))))) -> 0 | N37: =+'Brute allocat°'!P39-'Nette allocat°'!J37-'Nette allocat°'!K37+L37+M37 -> #N/A | O37: =+'Brute allocat°'!P39*17.4% -> #N/A | P37: =+'Brute allocat°'!P39*4% -> #N/A | Q37: =+'Brute allocat°'!P39+'Nette allocat°'!O37+'Nette allocat°'!P37 -> #N/A
A38: =+'Brute allocat°'!A40 -> 0 | B38: =+VLOOKUP(A38,'Salaire moyen'!$B$5:$O$43,14,FALSE) -> #N/A | E38: =+B38+C38+D38 -> #N/A | F38: =+E38/VLOOKUP(A38,'Salaire moyen'!$B$5:$Q$43,16,FALSE) -> #N/A | G38: =+IF(F38<=60000,0,IF(AND(F38>60000,F38<=150000),(INT(F38/1000)*1000-60000)*10%,IF(AND(F38>150000,F38<=250000),(INT(F38/1000)*1000-150000)*15%+9000,IF(AND(F38>250000,F38<=500000),(INT(F38/1000)*1000-250000)*19%+24000,IF(F38>500000,(INT(F38/1000)*1000-500000)*30%+71500))))) -> #N/A | I38: =+'Brute allocat°'!P40 -> #N/A | J38: =+((H37+I38)/F38)*G38 -> #N/A | K38: =+'Brute allocat°'!P40*3.6% -> #N/A | L38: =+IF(AND('Brute allocat°'!D40=Base!$C$3,'Brute allocat°'!B40=Base!$A$3),('Brute allocat°'!E40/(173.333333333333))*(NETWORKDAYS('Brute allocat°'!G40,'Brute allocat°'!F40)*8),IF(AND('Brute allocat°'!D40=Base!$C$3,'Brute allocat°'!B40=Base!$A$4,'Brute allocat°'!C40=Base!$B$5),'Brute allocat°'!E40,IF(AND('Brute allocat°'!D40=Base!$C$3,'Brute allocat°'!B40=Base!$A$4,'Brute allocat°'!C40=Base!$B$4),'Brute allocat°'!E40*3,IF(AND('Brute allocat°'!D40=Base!$C$5,'Brute allocat°'!B40=Base!$A$3),('Brute allocat°'!E40/(173.333333333333))*NETWORKDAYS('Brute allocat°'!G40,'Brute allocat°'!F40)*(-8),IF(AND('Brute allocat°'!D40=Base!$C$5,'Brute allocat°'!B40=Base!$A$4,'Brute allocat°'!C40=Base!$B$5),'Brute allocat°'!E40*(-1),IF(AND('Brute allocat°'!D40=Base!$C$5,'Brute allocat°'!C40=Base!$B$4),'Brute allocat°'!E40*(-3),0)))))) -> 0 | N38: =+'Brute allocat°'!P40-'Nette allocat°'!J38-'Nette allocat°'!K38+L38+M38 -> #N/A | O38: =+'Brute allocat°'!P40*17.4% -> #N/A | P38: =+'Brute allocat°'!P40*4% -> #N/A | Q38: =+'Brute allocat°'!P40+'Nette allocat°'!O38+'Nette allocat°'!P38 -> #N/A
A39: =+'Brute allocat°'!A41 -> 0 | B39: =+VLOOKUP(A39,'Salaire moyen'!$B$5:$O$43,14,FALSE) -> #N/A | E39: =+B39+C39+D39 -> #N/A | F39: =+E39/VLOOKUP(A39,'Salaire moyen'!$B$5:$Q$43,16,FALSE) -> #N/A | G39: =+IF(F39<=60000,0,IF(AND(F39>60000,F39<=150000),(INT(F39/1000)*1000-60000)*10%,IF(AND(F39>150000,F39<=250000),(INT(F39/1000)*1000-150000)*15%+9000,IF(AND(F39>250000,F39<=500000),(INT(F39/1000)*1000-250000)*19%+24000,IF(F39>500000,(INT(F39/1000)*1000-500000)*30%+71500))))) -> #N/A | I39: =+'Brute allocat°'!P41 -> #N/A | J39: =+((H38+I39)/F39)*G39 -> #N/A | K39: =+'Brute allocat°'!P41*3.6% -> #N/A | L39: =+IF(AND('Brute allocat°'!D41=Base!$C$3,'Brute allocat°'!B41=Base!$A$3),('Brute allocat°'!E41/(173.333333333333))*(NETWORKDAYS('Brute allocat°'!G41,'Brute allocat°'!F41)*8),IF(AND('Brute allocat°'!D41=Base!$C$3,'Brute allocat°'!B41=Base!$A$4,'Brute allocat°'!C41=Base!$B$5),'Brute allocat°'!E41,IF(AND('Brute allocat°'!D41=Base!$C$3,'Brute allocat°'!B41=Base!$A$4,'Brute allocat°'!C41=Base!$B$4),'Brute allocat°'!E41*3,IF(AND('Brute allocat°'!D41=Base!$C$5,'Brute allocat°'!B41=Base!$A$3),('Brute allocat°'!E41/(173.333333333333))*NETWORKDAYS('Brute allocat°'!G41,'Brute allocat°'!F41)*(-8),IF(AND('Brute allocat°'!D41=Base!$C$5,'Brute allocat°'!B41=Base!$A$4,'Brute allocat°'!C41=Base!$B$5),'Brute allocat°'!E41*(-1),IF(AND('Brute allocat°'!D41=Base!$C$5,'Brute allocat°'!C41=Base!$B$4),'Brute allocat°'!E41*(-3),0)))))) -> 0 | N39: =+'Brute allocat°'!P41-'Nette allocat°'!J39-'Nette allocat°'!K39+L39+M39 -> #N/A | O39: =+'Brute allocat°'!P41*17.4% -> #N/A | P39: =+'Brute allocat°'!P41*4% -> #N/A | Q39: =+'Brute allocat°'!P41+'Nette allocat°'!O39+'Nette allocat°'!P39 -> #N/A
A40: =+'Brute allocat°'!A42 -> 0 | B40: =+VLOOKUP(A40,'Salaire moyen'!$B$5:$O$43,14,FALSE) -> #N/A | E40: =+B40+C40+D40 -> #N/A | F40: =+E40/VLOOKUP(A40,'Salaire moyen'!$B$5:$Q$43,16,FALSE) -> #N/A | G40: =+IF(F40<=60000,0,IF(AND(F40>60000,F40<=150000),(INT(F40/1000)*1000-60000)*10%,IF(AND(F40>150000,F40<=250000),(INT(F40/1000)*1000-150000)*15%+9000,IF(AND(F40>250000,F40<=500000),(INT(F40/1000)*1000-250000)*19%+24000,IF(F40>500000,(INT(F40/1000)*1000-500000)*30%+71500))))) -> #N/A | I40: =+'Brute allocat°'!P42 -> #N/A | J40: =+((H39+I40)/F40)*G40 -> #N/A | K40: =+'Brute allocat°'!P42*3.6% -> #N/A | L40: =+IF(AND('Brute allocat°'!D42=Base!$C$3,'Brute allocat°'!B42=Base!$A$3),('Brute allocat°'!E42/(173.333333333333))*(NETWORKDAYS('Brute allocat°'!G42,'Brute allocat°'!F42)*8),IF(AND('Brute allocat°'!D42=Base!$C$3,'Brute allocat°'!B42=Base!$A$4,'Brute allocat°'!C42=Base!$B$5),'Brute allocat°'!E42,IF(AND('Brute allocat°'!D42=Base!$C$3,'Brute allocat°'!B42=Base!$A$4,'Brute allocat°'!C42=Base!$B$4),'Brute allocat°'!E42*3,IF(AND('Brute allocat°'!D42=Base!$C$5,'Brute allocat°'!B42=Base!$A$3),('Brute allocat°'!E42/(173.333333333333))*NETWORKDAYS('Brute allocat°'!G42,'Brute allocat°'!F42)*(-8),IF(AND('Brute allocat°'!D42=Base!$C$5,'Brute allocat°'!B42=Base!$A$4,'Brute allocat°'!C42=Base!$B$5),'Brute allocat°'!E42*(-1),IF(AND('Brute allocat°'!D42=Base!$C$5,'Brute allocat°'!C42=Base!$B$4),'Brute allocat°'!E42*(-3),0)))))) -> 0 | N40: =+'Brute allocat°'!P42-'Nette allocat°'!J40-'Nette allocat°'!K40+L40+M40 -> #N/A | O40: =+'Brute allocat°'!P42*17.4% -> #N/A | P40: =+'Brute allocat°'!P42*4% -> #N/A | Q40: =+'Brute allocat°'!P42+'Nette allocat°'!O40+'Nette allocat°'!P40 -> #N/A
A41: =+'Brute allocat°'!A43 -> 0 | B41: =+VLOOKUP(A41,'Salaire moyen'!$B$5:$O$43,14,FALSE) -> #N/A | E41: =+B41+C41+D41 -> #N/A | F41: =+E41/VLOOKUP(A41,'Salaire moyen'!$B$5:$Q$43,16,FALSE) -> #N/A | G41: =+IF(F41<=60000,0,IF(AND(F41>60000,F41<=150000),(INT(F41/1000)*1000-60000)*10%,IF(AND(F41>150000,F41<=250000),(INT(F41/1000)*1000-150000)*15%+9000,IF(AND(F41>250000,F41<=500000),(INT(F41/1000)*1000-250000)*19%+24000,IF(F41>500000,(INT(F41/1000)*1000-500000)*30%+71500))))) -> #N/A | I41: =+'Brute allocat°'!P43 -> #N/A | J41: =+((H40+I41)/F41)*G41 -> #N/A | K41: =+'Brute allocat°'!P43*3.6% -> #N/A | L41: =+IF(AND('Brute allocat°'!D43=Base!$C$3,'Brute allocat°'!B43=Base!$A$3),('Brute allocat°'!E43/(173.333333333333))*(NETWORKDAYS('Brute allocat°'!G43,'Brute allocat°'!F43)*8),IF(AND('Brute allocat°'!D43=Base!$C$3,'Brute allocat°'!B43=Base!$A$4,'Brute allocat°'!C43=Base!$B$5),'Brute allocat°'!E43,IF(AND('Brute allocat°'!D43=Base!$C$3,'Brute allocat°'!B43=Base!$A$4,'Brute allocat°'!C43=Base!$B$4),'Brute allocat°'!E43*3,IF(AND('Brute allocat°'!D43=Base!$C$5,'Brute allocat°'!B43=Base!$A$3),('Brute allocat°'!E43/(173.333333333333))*NETWORKDAYS('Brute allocat°'!G43,'Brute allocat°'!F43)*(-8),IF(AND('Brute allocat°'!D43=Base!$C$5,'Brute allocat°'!B43=Base!$A$4,'Brute allocat°'!C43=Base!$B$5),'Brute allocat°'!E43*(-1),IF(AND('Brute allocat°'!D43=Base!$C$5,'Brute allocat°'!C43=Base!$B$4),'Brute allocat°'!E43*(-3),0)))))) -> 0 | N41: =+'Brute allocat°'!P43-'Nette allocat°'!J41-'Nette allocat°'!K41+L41+M41 -> #N/A | O41: =+'Brute allocat°'!P43*17.4% -> #N/A | P41: =+'Brute allocat°'!P43*4% -> #N/A | Q41: =+'Brute allocat°'!P43+'Nette allocat°'!O41+'Nette allocat°'!P41 -> #N/A
A42: =+'Brute allocat°'!A44 -> 0 | B42: =+VLOOKUP(A42,'Salaire moyen'!$B$5:$O$43,14,FALSE) -> #N/A | E42: =+B42+C42+D42 -> #N/A | F42: =+E42/VLOOKUP(A42,'Salaire moyen'!$B$5:$Q$43,16,FALSE) -> #N/A | G42: =+IF(F42<=60000,0,IF(AND(F42>60000,F42<=150000),(INT(F42/1000)*1000-60000)*10%,IF(AND(F42>150000,F42<=250000),(INT(F42/1000)*1000-150000)*15%+9000,IF(AND(F42>250000,F42<=500000),(INT(F42/1000)*1000-250000)*19%+24000,IF(F42>500000,(INT(F42/1000)*1000-500000)*30%+71500))))) -> #N/A | I42: =+'Brute allocat°'!P44 -> #N/A | J42: =+((H41+I42)/F42)*G42 -> #N/A | K42: =+'Brute allocat°'!P44*3.6% -> #N/A | L42: =+IF(AND('Brute allocat°'!D44=Base!$C$3,'Brute allocat°'!B44=Base!$A$3),('Brute allocat°'!E44/(173.333333333333))*(NETWORKDAYS('Brute allocat°'!G44,'Brute allocat°'!F44)*8),IF(AND('Brute allocat°'!D44=Base!$C$3,'Brute allocat°'!B44=Base!$A$4,'Brute allocat°'!C44=Base!$B$5),'Brute allocat°'!E44,IF(AND('Brute allocat°'!D44=Base!$C$3,'Brute allocat°'!B44=Base!$A$4,'Brute allocat°'!C44=Base!$B$4),'Brute allocat°'!E44*3,IF(AND('Brute allocat°'!D44=Base!$C$5,'Brute allocat°'!B44=Base!$A$3),('Brute allocat°'!E44/(173.333333333333))*NETWORKDAYS('Brute allocat°'!G44,'Brute allocat°'!F44)*(-8),IF(AND('Brute allocat°'!D44=Base!$C$5,'Brute allocat°'!B44=Base!$A$4,'Brute allocat°'!C44=Base!$B$5),'Brute allocat°'!E44*(-1),IF(AND('Brute allocat°'!D44=Base!$C$5,'Brute allocat°'!C44=Base!$B$4),'Brute allocat°'!E44*(-3),0)))))) -> 0 | N42: =+'Brute allocat°'!P44-'Nette allocat°'!J42-'Nette allocat°'!K42+L42+M42 -> #N/A | O42: =+'Brute allocat°'!P44*17.4% -> #N/A | P42: =+'Brute allocat°'!P44*4% -> #N/A | Q42: =+'Brute allocat°'!P44+'Nette allocat°'!O42+'Nette allocat°'!P42 -> #N/A
A43: =+'Brute allocat°'!A45 -> 0 | B43: =+VLOOKUP(A43,'Salaire moyen'!$B$5:$O$43,14,FALSE) -> #N/A | E43: =+B43+C43+D43 -> #N/A | F43: =+E43/VLOOKUP(A43,'Salaire moyen'!$B$5:$Q$43,16,FALSE) -> #N/A | G43: =+IF(F43<=60000,0,IF(AND(F43>60000,F43<=150000),(INT(F43/1000)*1000-60000)*10%,IF(AND(F43>150000,F43<=250000),(INT(F43/1000)*1000-150000)*15%+9000,IF(AND(F43>250000,F43<=500000),(INT(F43/1000)*1000-250000)*19%+24000,IF(F43>500000,(INT(F43/1000)*1000-500000)*30%+71500))))) -> #N/A | I43: =+'Brute allocat°'!P45 -> #N/A | J43: =+((H42+I43)/F43)*G43 -> #N/A | K43: =+'Brute allocat°'!P45*3.6% -> #N/A | L43: =+IF(AND('Brute allocat°'!D45=Base!$C$3,'Brute allocat°'!B45=Base!$A$3),('Brute allocat°'!E45/(173.333333333333))*(NETWORKDAYS('Brute allocat°'!G45,'Brute allocat°'!F45)*8),IF(AND('Brute allocat°'!D45=Base!$C$3,'Brute allocat°'!B45=Base!$A$4,'Brute allocat°'!C45=Base!$B$5),'Brute allocat°'!E45,IF(AND('Brute allocat°'!D45=Base!$C$3,'Brute allocat°'!B45=Base!$A$4,'Brute allocat°'!C45=Base!$B$4),'Brute allocat°'!E45*3,IF(AND('Brute allocat°'!D45=Base!$C$5,'Brute allocat°'!B45=Base!$A$3),('Brute allocat°'!E45/(173.333333333333))*NETWORKDAYS('Brute allocat°'!G45,'Brute allocat°'!F45)*(-8),IF(AND('Brute allocat°'!D45=Base!$C$5,'Brute allocat°'!B45=Base!$A$4,'Brute allocat°'!C45=Base!$B$5),'Brute allocat°'!E45*(-1),IF(AND('Brute allocat°'!D45=Base!$C$5,'Brute allocat°'!C45=Base!$B$4),'Brute allocat°'!E45*(-3),0)))))) -> 0 | N43: =+'Brute allocat°'!P45-'Nette allocat°'!J43-'Nette allocat°'!K43+L43+M43 -> #N/A | O43: =+'Brute allocat°'!P45*17.4% -> #N/A | P43: =+'Brute allocat°'!P45*4% -> #N/A | Q43: =+'Brute allocat°'!P45+'Nette allocat°'!O43+'Nette allocat°'!P43 -> #N/A

Sheet Récap SDTCP
B5: ETAT DE SOLDE DE TOUT COMPTE DES CREDITS DE CONGES ET AUTRES DROITS
B7: Nom & Prénoms:
B8: Poste Occupé: | C8: Conseiller Relation Client à Distance
B9: Enfants à charge | C9: 0
B10: Nature de contrat | C10: =+VLOOKUP(C7,'Brute allocat°'!$A$7:$B$46,2,FALSE) -> CDD
B11: Date d'embauche: | C11: 45408
B12: Date de départ: | C12: =VLOOKUP(C7,'Brute allocat°'!$A$7:$N$46,7,FALSE) -> 45858
B13: Ancienneté: | C13: =DATEDIF(C11,C12,"y") & " Ans " &DATEDIF(C11,C12,"ym") & " Mois " &DATEDIF(C11,C12,"md") & " Jours " -> 1 Ans 2 Mois 24 Jours
B14: Salaire brut Moyen des 12 derniers mois: | C14: =+VLOOKUP(C7,'Salaire moyen'!$B$5:$P$43,15,FALSE) -> #N/A
C16: RUBRIQUES | E16: MONTANTS
B18: I- | C18: Congés payés
C19: Nombre de jours de crédits de congé à la date du | D19: =+C12 -> 45858 | E19: =+VLOOKUP(C7,'Brute allocat°'!$A$7:$L$46,12,FALSE) -> 29
C21: Allocation brute des crédits de congés | E21: =+VLOOKUP(C7,'Brute allocat°'!$A$7:$P$46,16,FALSE) -> #N/A
B23: II- | C23: Retenues Impôts & cotisations sociales
C25: CNSS | E25: =+VLOOKUP(C7,'Nette allocat°'!A4:K43,11,FALSE) -> #N/A
C26: ITS | E26: =+VLOOKUP(C7,'Nette allocat°'!A4:K43,10,FALSE) -> #N/A
C27: Total prélèvements | E27: =+E25+E26 -> #N/A
B29: III- | C29: =+IF(C10=Base!$A$3,"Côut des dommages et intérêts à payer pour rupture du contrat sans accord partie sur la période restante à courrir de",IF(C10=Base!$A$4,"Coût des dommages et intérêts à payer pour non respect de préavis de"," ")) -> Côut des dommages et intérêts à payer pour rupture du contrat sans accord partie sur la période restante à courrir de | D29: =+IF(C10=Base!$A$3,VLOOKUP('Récap SDTCP'!C7,'Brute allocat°'!$A$7:$M$46,13,FALSE),IF(AND('Récap SDTCP'!C10=Base!$A$4,VLOOKUP('Récap SDTCP'!C7,'Brute allocat°'!$A$7:$C$46,3,FALSE)=Base!$B$5),"1 mois",IF(AND('Récap SDTCP'!C10=Base!$A$4,VLOOKUP('Récap SDTCP'!C7,'Brute allocat°'!$A$7:$C$46,3,FALSE)=Base!$B$4),"3 mois"))) -> 1 mois 5 jours | E29: =+VLOOKUP(C7,'Nette allocat°'!A4:L43,12,FALSE) -> -203962.8
B32: IV- | C32: Préjudices/Autres retenues | E32: =+VLOOKUP(C7,'Nette allocat°'!$A$4:$M$43,13,FALSE) -> 0
B34: =+IF(C10=Base!$A$3," ",IF(C10=Base!$A$4,"V-")) | C34: =+IF(C10=Base!$A$4,"Rémunération des deux (02) jours de liberté de recherche d'emploi par semaine",IF('Récap SDTCP'!C10=Base!$A$3," ")) | D34: =+IF(C10=Base!$A$3," ",IF(AND(C10=Base!$A$4,VLOOKUP('Récap SDTCP'!C7,'Brute allocat°'!$A$7:$C$46,3,FALSE)=Base!$B$5),(VLOOKUP(C7,'Brute allocat°'!$A$7:$E$46,5,FALSE)/(2080/12))*8*8,IF(AND(C10,Base!$A$4,VLOOKUP(C7,'Brute allocat°'!$A$7:$C$46,3,FALSE)=Base!$B$4),(VLOOKUP(C7,'Brute allocat°'!$A$7:$E$46,5,FALSE)/(2080/12))*24*8)))
B36: =+IF(C10=Base!$A$3," ",IF(C10=Base!$A$4,"VI-")) | C36: =+IF(C10=Base!$A$4,"Rémunération calculée sur la période observée de préavis de",IF('Récap SDTCP'!C10=Base!$A$3," ")) | D36: =+IF(C10=Base!$A$4,NETWORKDAYS(VLOOKUP(C7,'Brute allocat°'!$A$7:$I$46,8,FALSE),VLOOKUP(C7,'Brute allocat°'!$A$7:$I$46,9,FALSE)) & " jours ouvrés ",IF(C10=Base!$A$3," ")) | E36: =+IF(C10=Base!$A$4,(VLOOKUP(C7,'Brute allocat°'!$A$7:$E$46,5,FALSE))/(173.333333333333)*(VLOOKUP(C7,'Brute allocat°'!$A$7:$N$46,14,FALSE)*8),0) -> 0
B38: =+IF(C10=Base!$A$4,"VII",IF(C10=Base!$A$3,"V")) -> V | C38: Net à payer | E38: =+IFERROR(E21-E27+E29+E32+D34+E36,E21-E27+E29) -> #N/A
B40: TOTAL A PAYER | E40: =E38 -> #N/A
B42: ARRETE LE PRESENT ETAT A LA SOMME DE FCFA : MOINS QUATRE VINGT DIX-NEUF MILLE DIX HUIT FRANCS CFA
B45: Etabli par : | C45: Controlé par : | D45: Visé par : | E45: Approuvé par :
B46: Thola AGBOTON | C46: Damien VODOUMBO | D46: Urbain AHITCHEMIN | E46: Michèle Claudine Claire Bai DEGBOE
B47: ARH | C47: RFC ADJOINT | D47: DCH | E47: DGA-SUPPORT
D51: Lu et approuvé par | E51: =+C7 -> 0

Sheet Base
A2: Statut | B2: Catégorie | C2: Nature de la rupture
A3: CDD | B3: RAS | C3: Rupture abusive de l'employeur
A4: CDI | B4: Agents de maîtrise, cadres et assimilés | C4: Rupture de l'employé sur accord partie
B5: Employés, ouvriers et manœuvres | C5: Rupture de l'employé sans accord partie
C6: Rupture pour faute lourde
